Workbook
Name CATEGORIE: 'Rischi per aree PAC'!$D$1:$D$5
Name COMPLIANCE: 'Rischi per aree PAC'!$J$1:$J$6
Name ESTERNI: 'Rischi per aree PAC'!$F$1:$F$5
Name FINANZIARI: 'Rischi per aree PAC'!$G$1:$G$5
Name Informativa_e_reporting: Appoggio!$R$54:$R$56
Name nessuno: 'Rischi per aree PAC'!$L$1
Name OPERATIVI: 'Rischi per aree PAC'!$I$1:$I$2
Name Rischio_Clinico_Sanitario: Appoggio!$Q$3:$Q$16
Name Rischio_di_Compliance: Appoggio!$Q$46:$Q$51
Name Rischio_Esterno: Appoggio!$Q$17:$Q$22
Name Rischio_Finanziario: Appoggio!$Q$23:$Q$27
Name Rischio_Operativo: Appoggio!$Q$34:$Q$45
Name Rischio_Strategico: Appoggio!$Q$28:$Q$33
Name Salute_sicurezza_e_ambiente: Appoggio!$R$57:$R$68
Name strategici: 'Rischi per aree PAC'!$H$1:$H$6

Sheet Copertina
H2: Logo Struttura
A12: RISK REGISTER - PAC AREA D IMMOBILIZZAZIONI
A14: Registro dei Rischi
A16: Risk Guide
A18: Risk Model
A20: Metriche di Valutazione

Sheet Registro dei Rischi
C2: RISK REGISTER - PAC AREA D IMMOBILIZZAZIONI
C5: OWNERSHIP DEL RISCHIO | H5: ANAGRAFICA DEL RISCHIO | L5: ANALISI DEL RISCHIO | N5: VALUTAZIONE RISCHIO INERENTE | X5: VALUTAZIONE SISTEMA DI CONTROLLI IN ESSERE | AN5: VALUTAZIONE RISCHIO RESIDUO | AT5: VALUTAZIONE RISCHIO RESIDUO | AW5: AZIONI | AX5: VALUTAZIONE AZIONI DI MITIGAZIONE E MIGLIORAMENTO | BB5: VALUTAZIONE RISCHIO RESIDUO TO-BE
C6: # Rischio | D6: ID Rischio | E6: Direzione | F6: Risk Owner | G6: Processo | H6: Categoria Rischio Livello 1 | I6: Categoria Rischio Livello 2 | J6: Categoria Rischio Livello 3 | K6: Scenario di rischio | L6: Principali cause del rischio | M6: Principali conseguenze del rischio | N6: Valutazione del rischio | O6: Economico-Finanziario | P6: Reputazionale | Q6: Salute e Sicurezza | R6: Compliance | S6: Gestionale - Operativo | T6: Ambiente | U6: Impatto Inerente | V6: Probabilità Inerente | W6: RPN Inerente | X6: Mitigazioni operative CORRETTIVE in essere | Y6: Valutazione controlli su impatto eco-fin | Z6: Valutazione controlli su impatto reputazionale | AA6: Valutazione controlli su impatto salute e sicurezza | AB6: Valutazione controlli su impatto compliance | AC6: Valutazione controlli su impatto gest-ope | AD6: Valutazione controlli su impatto ambientale | AE6: Fattore riduzione impatto eco-fin | AF6: Fattore riduzione impatto reputazionale | AG6: Fattore riduzione impatto salute e sicurezza | AH6: Fattore riduzione impatto compliance | AI6: Fattore riduzione impatto gest-ope | AJ6: Fattore riduzione impatto ambientale | AK6: Mitigazioni operative PREVENTIVE in essere | AL6: Valutazione controlli preventivi | AM6: Fattore riduzione probabilità | AN6: Economico-Finanziario | AO6: Reputazionale | AP6: Salute e Sicurezza | AQ6: Compliance | AR6: Gestionale- Operativo | AS6: Ambiente | AT6: Impatto Residuo | AU6: Probabilità Residua | AV6: RPN Residuo | AW6: Azioni di mitigazione e miglioramento | AX6: Efficacia delle azioni CORRETTIVE | AY6: Fattore riduzione impatto | AZ6: Efficacia delle azioni PREVENTIVE | BA6: Fattore riduzione probabilità | BB6: Impatto Residuo to-be | BC6: Probabilità residua to-be | BD6: RPN Residuo to-be
C7: 1 | D7: PAC_D_01 | E7: Direzione Sanitaria | F7: Direttore Ingegneria Clinica | G7: PAC Area D - Immobilizzazioni / Ingegneria Clinica | H7: Rischio Operativo | I7: Attività, processi e procedure | K7: Errata o incompleta ricezione, presa in carico e registrazione dei beni in ingresso. | L7: Processi: - DDT, ordine e bolla di carico non riconciliati - Mancata registrazione o registrazione tardiva in NFS - Consegna diretta al reparto senza completa trasmissione documentale Persone: - Mancata segnalazione di anomalie o difformità alla consegna Fattori esterni: - Consegne urgenti o apparecchiature ingombranti con iter logistico speciale Strumenti: - | M7: Economiche: Errata rappresentazione del patrimonio e possibili extra costi per contestazioni tardive Danno d'immagine: Rilievi in sede PAC/audit Salute e sicurezza: Rischio indiretto per utilizzo di bene non completamente verificato Compliance normativa: Non conformità a procedura di ricevimento e presa in carico Gestionale - Operativo: Ritardo in inventariazione, collaudo e disponibilità operativa Ambiente: - | N7: Il rischio incide sulla completezza del ciclo cespiti e sulla tracciabilità documentale DDT-ordine-carico; i controlli di magazzino e IC riducono l'esposizione. | O7: 3 | P7: 2 | Q7: 2 | R7: 5 | S7: 5 | T7: N.A. | U7: =IF(AND(OR(O7="",O7="N.A."),OR(P7="",P7="N.A."),OR(Q7="",Q7="N.A."),OR(R7="",R7="N.A."),OR(S7="",S7="N.A."),OR(T7="",T7="N.A.")),"N.A.",MAX(O7:T7)) -> 5 | V7: 3 | W7: =IF(OR(U7="N.A.",V7="",V7="N.A."),"N.A.",U7*V7) -> 15 | X7: Regolarizzazione della documentazione di consegna; contestazione al fornitore; riallineamento del carico NFS e blocco temporaneo dell'iter di collaudo se necessario. | Y7: 3 | Z7: 4 | AA7: 3 | AB7: 3 | AC7: 3 | AE7: =IF(Y7="","",VLOOKUP(Y7,Appoggio!$M$3:$N$7,2,0)) -> 0.25 | AF7: =IF(Z7="","",VLOOKUP(Z7,Appoggio!$M$3:$N$7,2,0)) -> 0.1 | AG7: =IF(AA7="","",VLOOKUP(AA7,Appoggio!$M$3:$N$7,2,0)) -> 0.25 | AH7: =IF(AB7="","",VLOOKUP(AB7,Appoggio!$M$3:$N$7,2,0)) -> 0.25 | AI7: =IF(AC7="","",VLOOKUP(AC7,Appoggio!$M$3:$N$7,2,0)) -> 0.25 | AJ7: =IF(AD7="","",VLOOKUP(AD7,Appoggio!$M$3:$N$7,2,0)) | AK7: Verifica DDT e integrità imballo; registrazione carico in NFS; invio copia DDT/carico/ordine e coordinamento tra Magazzino, Approvvigionamenti e Ingegneria Clinica. | AL7: 4 | AM7: =IF(AL7="","",VLOOKUP(AL7,Appoggio!$M$3:$N$7,2,0)) -> 0.1 | AN7: =IF(OR(O7="N.A.",O7="",AE7=""),"N.A.",O7*AE7) -> 0.75 | AO7: =IF(OR(P7="N.A.",P7="",AF7=""),"N.A.",P7*AF7) -> 0.2 | AP7: =IF(OR(Q7="N.A.",Q7="",AG7=""),"N.A.",Q7*AG7) -> 0.5 | AQ7: =IF(OR(R7="N.A.",R7="",AH7=""),"N.A.",R7*AH7) -> 1.25 | AR7: =IF(OR(S7="N.A.",S7="",AI7=""),"N.A.",S7*AI7) -> 1.25 | AS7: =IF(OR(T7="N.A.",T7="",AJ7=""),"N.A.",T7*AJ7) -> N.A. | AT7: =IF(AND(OR(AN7="",AN7="N.A."),OR(AO7="",AO7="N.A."),OR(AP7="",AP7="N.A."),OR(AQ7="",AQ7="N.A."),OR(AR7="",AR7="N.A."),OR(AS7="",AS7="N.A.")),"N.A.",MAX(AN7:AS7)) -> 1.25 | AU7: =IF(OR(V7="",V7="N.A.",AM7=""),"N.A.",V7*AM7) -> 0.3 | AV7: =IF(OR(AT7="N.A.",AU7="N.A."),"N.A.",ROUND(AT7*AU7,1)) -> 0.4 | AY7: =IF(AX7="","",VLOOKUP(AX7,Appoggio!$M$3:$N$7,2,0)) | BA7: =IF(AZ7="","",VLOOKUP(AZ7,Appoggio!$M$3:$N$7,2,0)) | BB7: =IF(AY7="",AT7,IF(AT7="N.A.","N.A.",AT7*AY7)) -> 1.25 | BC7: =IF(BA7="",AU7,IF(AU7="N.A.","N.A.",AU7*BA7)) -> 0.3 | BD7: =IF(OR(BB7="N.A.",BC7="N.A."),"N.A.",ROUND(BB7*BC7,1)) -> 0.4
C8: 2 | D8: PAC_D_02 | E8: Direzione Sanitaria | F8: Direttore Ingegneria Clinica | G8: PAC Area D - Immobilizzazioni / Ingegneria Clinica | H8: Rischio Finanziario | I8: Contabilità e reporting finanziario | K8: Mancata, incompleta o errata iscrizione a libro cespiti delle apparecchiature elettromedicali di proprietà. | L8: Processi: - Mancata ricezione di DDT, carico o fotocopia etichetta - Dati anagrafici tecnici/organizzativi incompleti - Mancato collegamento tra scheda cespite e fonte di finanziamento Persone: - Errori di data entry o controlli non tempestivi Fattori esterni: - Strumenti: - Anagrafica NFS incompleta o non aggiornata | M8: Economiche: Errore nel valore del patrimonio e negli ammortamenti Danno d'immagine: Possibili rilievi PAC o revisori Salute e sicurezza: Rischio indiretto per mancata correlazione a manutenzione/collaudo Compliance normativa: Non conformità a DGR PAC Area D e procedure interne Gestionale - Operativo: Disallineamento tra inventario fisico, tecnico e libro cespiti Ambiente: - | N8: Il libro cespiti è presidio centrale PAC; impatto economico/compliance significativo in caso di incompletezza. | O8: 5 | P8: 2 | Q8: 2 | R8: 5 | S8: 5 | T8: N.A. | U8: =IF(AND(OR(O8="",O8="N.A."),OR(P8="",P8="N.A."),OR(Q8="",Q8="N.A."),OR(R8="",R8="N.A."),OR(S8="",S8="N.A."),OR(T8="",T8="N.A.")),"N.A.",MAX(O8:T8)) -> 5 | V8: 3 | W8: =IF(OR(U8="N.A.",V8="",V8="N.A."),"N.A.",U8*V8) -> 15 | X8: Rettifica anagrafica cespite; riconciliazione con DDT, ordine, bolla di carico, etichetta e verbale di collaudo. | Y8: 3 | Z8: 4 | AA8: 3 | AB8: 3 | AC8: 3 | AE8: =IF(Y8="","",VLOOKUP(Y8,Appoggio!$M$3:$N$7,2,0)) -> 0.25 | AF8: =IF(Z8="","",VLOOKUP(Z8,Appoggio!$M$3:$N$7,2,0)) -> 0.1 | AG8: =IF(AA8="","",VLOOKUP(AA8,Appoggio!$M$3:$N$7,2,0)) -> 0.25 | AH8: =IF(AB8="","",VLOOKUP(AB8,Appoggio!$M$3:$N$7,2,0)) -> 0.25 | AI8: =IF(AC8="","",VLOOKUP(AC8,Appoggio!$M$3:$N$7,2,0)) -> 0.25 | AJ8: =IF(AD8="","",VLOOKUP(AD8,Appoggio!$M$3:$N$7,2,0)) | AK8: Doppia inventariazione tecnica/patrimoniale; invio documenti da Magazzino/Approvvigionamenti; abbinamento bolla-fattura e controlli su anagrafica cespite. | AL8: 4 | AM8: =IF(AL8="","",VLOOKUP(AL8,Appoggio!$M$3:$N$7,2,0)) -> 0.1 | AN8: =IF(OR(O8="N.A.",O8="",AE8=""),"N.A.",O8*AE8) -> 1.25 | AO8: =IF(OR(P8="N.A.",P8="",AF8=""),"N.A.",P8*AF8) -> 0.2 | AP8: =IF(OR(Q8="N.A.",Q8="",AG8=""),"N.A.",Q8*AG8) -> 0.5 | AQ8: =IF(OR(R8="N.A.",R8="",AH8=""),"N.A.",R8*AH8) -> 1.25 | AR8: =IF(OR(S8="N.A.",S8="",AI8=""),"N.A.",S8*AI8) -> 1.25 | AS8: =IF(OR(T8="N.A.",T8="",AJ8=""),"N.A.",T8*AJ8) -> N.A. | AT8: =IF(AND(OR(AN8="",AN8="N.A."),OR(AO8="",AO8="N.A."),OR(AP8="",AP8="N.A."),OR(AQ8="",AQ8="N.A."),OR(AR8="",AR8="N.A."),OR(AS8="",AS8="N.A.")),"N.A.",MAX(AN8:AS8)) -> 1.25 | AU8: =IF(OR(V8="",V8="N.A.",AM8=""),"N.A.",V8*AM8) -> 0.3 | AV8: =IF(OR(AT8="N.A.",AU8="N.A."),"N.A.",ROUND(AT8*AU8,1)) -> 0.4 | AY8: =IF(AX8="","",VLOOKUP(AX8,Appoggio!$M$3:$N$7,2,0)) | BA8: =IF(AZ8="","",VLOOKUP(AZ8,Appoggio!$M$3:$N$7,2,0)) | BB8: =IF(AY8="",AT8,IF(AT8="N.A.","N.A.",AT8*AY8)) -> 1.25 | BC8: =IF(BA8="",AU8,IF(AU8="N.A.","N.A.",AU8*BA8)) -> 0.3 | BD8: =IF(OR(BB8="N.A.",BC8="N.A."),"N.A.",ROUND(BB8*BC8,1)) -> 0.4
C9: 3 | D9: PAC_D_03 | E9: Direzione Sanitaria | F9: Direttore Ingegneria Clinica | G9: PAC Area D - Immobilizzazioni / Ingegneria Clinica | H9: Rischio Operativo | I9: Attività, processi e procedure | K9: Errata gestione dei beni di terzi acquisiti in comodato, service, noleggio o leasing. | L9: Processi: - Mancata registrazione dei beni di terzi nel libro inventari - Classificazione errata come bene ammortizzabile - Iter deliberativo di comodato/service/noleggio non concluso prima della presa in carico Persone: - Comunicazioni incomplete tra Approvvigionamenti, Ingegneria Clinica e UO utilizzatrice Fattori esterni: - Contratti o service complessi con sostituzioni temporanee o apparecchiature multiple Strumenti: - | M9: Economiche: Errata rappresentazione patrimoniale e possibili costi non previsti Danno d'immagine: Rilievi in audit o da terzi proprietari Salute e sicurezza: Rischio indiretto se bene non correttamente censito per manutenzione/collaudo Compliance normativa: Non conformità agli obblighi contrattuali e inventariali Gestionale - Operativo: Difficoltà di tracciabilità, restituzione o dismissione Ambiente: - | N9: Rischio PAC specifico per corretta separazione tra beni propri e di terzi; impatto principale compliance/gestionale. | O9: 3 | P9: 2 | Q9: 3 | R9: 5 | S9: 5 | T9: N.A. | U9: =IF(AND(OR(O9="",O9="N.A."),OR(P9="",P9="N.A."),OR(Q9="",Q9="N.A."),OR(R9="",R9="N.A."),OR(S9="",S9="N.A."),OR(T9="",T9="N.A.")),"N.A.",MAX(O9:T9)) -> 5 | V9: 3 | W9: =IF(OR(U9="N.A.",V9="",V9="N.A."),"N.A.",U9*V9) -> 15 | X9: Rettifica classificazione; aggiornamento libro inventari e fascicolo tecnico; verifica contratto/atto di comodato/service/noleggio. | Y9: 3 | Z9: 4 | AA9: 3 | AB9: 3 | AC9: 3 | AE9: =IF(Y9="","",VLOOKUP(Y9,Appoggio!$M$3:$N$7,2,0)) -> 0.25 | AF9: =IF(Z9="","",VLOOKUP(Z9,Appoggio!$M$3:$N$7,2,0)) -> 0.1 | AG9: =IF(AA9="","",VLOOKUP(AA9,Appoggio!$M$3:$N$7,2,0)) -> 0.25 | AH9: =IF(AB9="","",VLOOKUP(AB9,Appoggio!$M$3:$N$7,2,0)) -> 0.25 | AI9: =IF(AC9="","",VLOOKUP(AC9,Appoggio!$M$3:$N$7,2,0)) -> 0.25 | AJ9: =IF(AD9="","",VLOOKUP(AD9,Appoggio!$M$3:$N$7,2,0)) | AK9: Accettazione fisica e contabile gestita da Approvvigionamenti; registrazione come bene non soggetto ad ammortamento; censimento tecnico da Global Service/Ingegneria Clinica. | AL9: 4 | AM9: =IF(AL9="","",VLOOKUP(AL9,Appoggio!$M$3:$N$7,2,0)) -> 0.1 | AN9: =IF(OR(O9="N.A.",O9="",AE9=""),"N.A.",O9*AE9) -> 0.75 | AO9: =IF(OR(P9="N.A.",P9="",AF9=""),"N.A.",P9*AF9) -> 0.2 | AP9: =IF(OR(Q9="N.A.",Q9="",AG9=""),"N.A.",Q9*AG9) -> 0.75 | AQ9: =IF(OR(R9="N.A.",R9="",AH9=""),"N.A.",R9*AH9) -> 1.25 | AR9: =IF(OR(S9="N.A.",S9="",AI9=""),"N.A.",S9*AI9) -> 1.25 | AS9: =IF(OR(T9="N.A.",T9="",AJ9=""),"N.A.",T9*AJ9) -> N.A. | AT9: =IF(AND(OR(AN9="",AN9="N.A."),OR(AO9="",AO9="N.A."),OR(AP9="",AP9="N.A."),OR(AQ9="",AQ9="N.A."),OR(AR9="",AR9="N.A."),OR(AS9="",AS9="N.A.")),"N.A.",MAX(AN9:AS9)) -> 1.25 | AU9: =IF(OR(V9="",V9="N.A.",AM9=""),"N.A.",V9*AM9) -> 0.3 | AV9: =IF(OR(AT9="N.A.",AU9="N.A."),"N.A.",ROUND(AT9*AU9,1)) -> 0.4 | AY9: =IF(AX9="","",VLOOKUP(AX9,Appoggio!$M$3:$N$7,2,0)) | BA9: =IF(AZ9="","",VLOOKUP(AZ9,Appoggio!$M$3:$N$7,2,0)) | BB9: =IF(AY9="",AT9,IF(AT9="N.A.","N.A.",AT9*AY9)) -> 1.25 | BC9: =IF(BA9="",AU9,IF(AU9="N.A.","N.A.",AU9*BA9)) -> 0.3 | BD9: =IF(OR(BB9="N.A.",BC9="N.A."),"N.A.",ROUND(BB9*BC9,1)) -> 0.4
C10: 4 | D10: PAC_D_04 | E10: Direzione Sanitaria | F10: Direttore Ingegneria Clinica | G10: PAC Area D - Immobilizzazioni / Ingegneria Clinica | H10: Rischio Finanziario | I10: Contabilità e reporting finanziario | K10: Errata valorizzazione iniziale del cespite, inclusi oneri accessori, trasporto, IVA non detraibile o valore di donazione. | L10: Processi: - Costi accessori non comunicati o non inclusi - Valutazione donazione basata su documentazione incompleta - Informazioni tecniche aggiuntive non fornite all'inventario patrimoniale Persone: - Errori di interpretazione tra ordine, fattura e documenti di donazione Fattori esterni: - Strumenti: - Scheda cespite non integrata con tutte le componenti di costo | M10: Economiche: Sovra/sottostima del valore iniziale e degli ammortamenti Danno d'immagine: Rilievi PAC/revisori Salute e sicurezza: Possibile ritardo in accettazione donazione per verifica conformità Compliance normativa: Non conformità a principi contabili e procedure Area D Gestionale - Operativo: Necessità di rettifiche e ricostruzioni documentali Ambiente: - | N10: L'impatto economico è significativo perché il valore iniziale condiziona patrimonio, ammortamenti e sterilizzazioni. | O10: 5 | P10: 2 | Q10: 2 | R10: 5 | S10: 3 | T10: N.A. | U10: =IF(AND(OR(O10="",O10="N.A."),OR(P10="",P10="N.A."),OR(Q10="",Q10="N.A."),OR(R10="",R10="N.A."),OR(S10="",S10="N.A."),OR(T10="",T10="N.A.")),"N.A.",MAX(O10:T10)) -> 5 | V10: 3 | W10: =IF(OR(U10="N.A.",V10="",V10="N.A."),"N.A.",U10*V10) -> 15 | X10: Rettifica del valore cespite e della documentazione di supporto; riallineamento con fattura/ordine/stima del donante. | Y10: 3 | Z10: 4 | AA10: 3 | AB10: 3 | AC10: 3 | AE10: =IF(Y10="","",VLOOKUP(Y10,Appoggio!$M$3:$N$7,2,0)) -> 0.25 | AF10: =IF(Z10="","",VLOOKUP(Z10,Appoggio!$M$3:$N$7,2,0)) -> 0.1 | AG10: =IF(AA10="","",VLOOKUP(AA10,Appoggio!$M$3:$N$7,2,0)) -> 0.25 | AH10: =IF(AB10="","",VLOOKUP(AB10,Appoggio!$M$3:$N$7,2,0)) -> 0.25 | AI10: =IF(AC10="","",VLOOKUP(AC10,Appoggio!$M$3:$N$7,2,0)) -> 0.25 | AJ10: =IF(AD10="","",VLOOKUP(AD10,Appoggio!$M$3:$N$7,2,0)) | AK10: Valorizzazione definita da Approvvigionamenti; collaborazione propositiva di Ingegneria Clinica su informazioni non desumibili dall'ordine; controlli su fatture e stime documentate. | AL10: 4 | AM10: =IF(AL10="","",VLOOKUP(AL10,Appoggio!$M$3:$N$7,2,0)) -> 0.1 | AN10: =IF(OR(O10="N.A.",O10="",AE10=""),"N.A.",O10*AE10) -> 1.25 | AO10: =IF(OR(P10="N.A.",P10="",AF10=""),"N.A.",P10*AF10) -> 0.2 | AP10: =IF(OR(Q10="N.A.",Q10="",AG10=""),"N.A.",Q10*AG10) -> 0.5 | AQ10: =IF(OR(R10="N.A.",R10="",AH10=""),"N.A.",R10*AH10) -> 1.25 | AR10: =IF(OR(S10="N.A.",S10="",AI10=""),"N.A.",S10*AI10) -> 0.75 | AS10: =IF(OR(T10="N.A.",T10="",AJ10=""),"N.A.",T10*AJ10) -> N.A. | AT10: =IF(AND(OR(AN10="",AN10="N.A."),OR(AO10="",AO10="N.A."),OR(AP10="",AP10="N.A."),OR(AQ10="",AQ10="N.A."),OR(AR10="",AR10="N.A."),OR(AS10="",AS10="N.A.")),"N.A.",MAX(AN10:AS10)) -> 1.25 | AU10: =IF(OR(V10="",V10="N.A.",AM10=""),"N.A.",V10*AM10) -> 0.3 | AV10: =IF(OR(AT10="N.A.",AU10="N.A."),"N.A.",ROUND(AT10*AU10,1)) -> 0.4 | AY10: =IF(AX10="","",VLOOKUP(AX10,Appoggio!$M$3:$N$7,2,0)) | BA10: =IF(AZ10="","",VLOOKUP(AZ10,Appoggio!$M$3:$N$7,2,0)) | BB10: =IF(AY10="",AT10,IF(AT10="N.A.","N.A.",AT10*AY10)) -> 1.25 | BC10: =IF(BA10="",AU10,IF(AU10="N.A.","N.A.",AU10*BA10)) -> 0.3 | BD10: =IF(OR(BB10="N.A.",BC10="N.A."),"N.A.",ROUND(BB10*BC10,1)) -> 0.4
C11: 5 | D11: PAC_D_05 | E11: Direzione Sanitaria | F11: Direttore Ingegneria Clinica | G11: PAC Area D - Immobilizzazioni / Ingegneria Clinica | H11: Rischio Finanziario | I11: Contabilità e reporting finanziario | K11: Mancata o errata registrazione della data di collaudo con riflessi sulla decorrenza dell'ammortamento. | L11: Processi: - Verbale di collaudo non trasmesso tempestivamente - Esito collaudo non correttamente formalizzato - Campo data collaudo in anagrafica cespite incompleto o errato Persone: - Mancata comunicazione tra Ingegneria Clinica e Approvvigionamenti Fattori esterni: - Collaudo sospeso, negativo o condizionato a sanatorie documentali/tecniche Strumenti: - | M11: Economiche: Ammortamento avviato in periodo errato o non avviato Danno d'immagine: Rilievi su cut-off e correttezza contabile Salute e sicurezza: Possibile utilizzo senza completa presa in consegna/addestramento Compliance normativa: Non conformità a procedura PO 595 e criteri contabili Gestionale - Operativo: Ritardi in messa in servizio o in chiusura pratica Ambiente: - | N11: Il periodo di ammortamento decorre dall'esito positivo del collaudo; il rischio è quindi rilevante per cut-off contabile. | O11: 5 | P11: 2 | Q11: 3 | R11: 5 | S11: 5 | T11: N.A. | U11: =IF(AND(OR(O11="",O11="N.A."),OR(P11="",P11="N.A."),OR(Q11="",Q11="N.A."),OR(R11="",R11="N.A."),OR(S11="",S11="N.A."),OR(T11="",T11="N.A.")),"N.A.",MAX(O11:T11)) -> 5 | V11: 3 | W11: =IF(OR(U11="N.A.",V11="",V11="N.A."),"N.A.",U11*V11) -> 15 | X11: Rettifica data collaudo in NFS; recupero verbale firmato; verifica eventuale sospensione/ritardo e allineamento ammortamenti. | Y11: 3 | Z11: 4 | AA11: 4 | AB11: 3 | AC11: 3 | AE11: =IF(Y11="","",VLOOKUP(Y11,Appoggio!$M$3:$N$7,2,0)) -> 0.25 | AF11: =IF(Z11="","",VLOOKUP(Z11,Appoggio!$M$3:$N$7,2,0)) -> 0.1 | AG11: =IF(AA11="","",VLOOKUP(AA11,Appoggio!$M$3:$N$7,2,0)) -> 0.1 | AH11: =IF(AB11="","",VLOOKUP(AB11,Appoggio!$M$3:$N$7,2,0)) -> 0.25 | AI11: =IF(AC11="","",VLOOKUP(AC11,Appoggio!$M$3:$N$7,2,0)) -> 0.25 | AJ11: =IF(AD11="","",VLOOKUP(AD11,Appoggio!$M$3:$N$7,2,0)) | AK11: Verbale di collaudo sottoscritto e trasmesso ad Approvvigionamenti; registrazione degli estremi del collaudo in anagrafica cespite. | AL11: 4 | AM11: =IF(AL11="","",VLOOKUP(AL11,Appoggio!$M$3:$N$7,2,0)) -> 0.1 | AN11: =IF(OR(O11="N.A.",O11="",AE11=""),"N.A.",O11*AE11) -> 1.25 | AO11: =IF(OR(P11="N.A.",P11="",AF11=""),"N.A.",P11*AF11) -> 0.2 | AP11: =IF(OR(Q11="N.A.",Q11="",AG11=""),"N.A.",Q11*AG11) -> 0.3 | AQ11: =IF(OR(R11="N.A.",R11="",AH11=""),"N.A.",R11*AH11) -> 1.25 | AR11: =IF(OR(S11="N.A.",S11="",AI11=""),"N.A.",S11*AI11) -> 1.25 | AS11: =IF(OR(T11="N.A.",T11="",AJ11=""),"N.A.",T11*AJ11) -> N.A. | AT11: =IF(AND(OR(AN11="",AN11="N.A."),OR(AO11="",AO11="N.A."),OR(AP11="",AP11="N.A."),OR(AQ11="",AQ11="N.A."),OR(AR11="",AR11="N.A."),OR(AS11="",AS11="N.A.")),"N.A.",MAX(AN11:AS11)) -> 1.25 | AU11: =IF(OR(V11="",V11="N.A.",AM11=""),"N.A.",V11*AM11) -> 0.3 | AV11: =IF(OR(AT11="N.A.",AU11="N.A."),"N.A.",ROUND(AT11*AU11,1)) -> 0.4 | AY11: =IF(AX11="","",VLOOKUP(AX11,Appoggio!$M$3:$N$7,2,0)) | BA11: =IF(AZ11="","",VLOOKUP(AZ11,Appoggio!$M$3:$N$7,2,0)) | BB11: =IF(AY11="",AT11,IF(AT11="N.A.","N.A.",AT11*AY11)) -> 1.25 | BC11: =IF(BA11="",AU11,IF(AU11="N.A.","N.A.",AU11*BA11)) -> 0.3 | BD11: =IF(OR(BB11="N.A.",BC11="N.A."),"N.A.",ROUND(BB11*BC11,1)) -> 0.4
C12: 6 | D12: PAC_D_06 | E12: Direzione Sanitaria | F12: Direttore Ingegneria Clinica | G12: PAC Area D - Immobilizzazioni / Ingegneria Clinica | H12: Rischio Finanziario | I12: Contabilità e reporting finanziario | K12: Errato calcolo o applicazione delle aliquote di ammortamento e delle sterilizzazioni. | L12: Processi: - Aliquota non coerente con classificazione cespite - Mancato aggiornamento della tabella ammortamenti/sterilizzazioni - Controlli trimestrali non efficaci Persone: - Errori di configurazione o verifica contabile Fattori esterni: - Strumenti: - Piattaforma NFS - Dedalus con dati anagrafici non corretti | M12: Economiche: Errore in ammortamenti, sterilizzazioni, conto economico e valore netto contabile Danno d'immagine: Rilievi da revisori, audit e PAC Salute e sicurezza: - Compliance normativa: Non conformità al D.Lgs 118/2011 e indicazioni regionali Gestionale - Operativo: Rettifiche contabili e ritardi nella chiusura periodica Ambiente: - | N12: Rischio finanziario diretto; mitigato dal calcolo in piattaforma e verifica trimestrale Economico-Finanziaria. | O12: 7 | P12: 2 | Q12: N.A. | R12: 5 | S12: 3 | T12: N.A. | U12: =IF(AND(OR(O12="",O12="N.A."),OR(P12="",P12="N.A."),OR(Q12="",Q12="N.A."),OR(R12="",R12="N.A."),OR(S12="",S12="N.A."),OR(T12="",T12="N.A.")),"N.A.",MAX(O12:T12)) -> 7 | V12: 3 | W12: =IF(OR(U12="N.A.",V12="",V12="N.A."),"N.A.",U12*V12) -> 21 | X12: Ricalcolo ammortamenti/sterilizzazioni; rettifica aliquota/classificazione cespite; quadratura con contabilità generale. | Y12: 3 | Z12: 4 | AB12: 3 | AC12: 3 | AE12: =IF(Y12="","",VLOOKUP(Y12,Appoggio!$M$3:$N$7,2,0)) -> 0.25 | AF12: =IF(Z12="","",VLOOKUP(Z12,Appoggio!$M$3:$N$7,2,0)) -> 0.1 | AG12: =IF(AA12="","",VLOOKUP(AA12,Appoggio!$M$3:$N$7,2,0)) | AH12: =IF(AB12="","",VLOOKUP(AB12,Appoggio!$M$3:$N$7,2,0)) -> 0.25 | AI12: =IF(AC12="","",VLOOKUP(AC12,Appoggio!$M$3:$N$7,2,0)) -> 0.25 | AJ12: =IF(AD12="","",VLOOKUP(AD12,Appoggio!$M$3:$N$7,2,0)) | AK12: Calcolo su piattaforma NFS-Dedalus; verifica trimestrale della corrispondenza delle aliquote e allineamento con anagrafica cespiti. | AL12: 4 | AM12: =IF(AL12="","",VLOOKUP(AL12,Appoggio!$M$3:$N$7,2,0)) -> 0.1 | AN12: =IF(OR(O12="N.A.",O12="",AE12=""),"N.A.",O12*AE12) -> 1.75 | AO12: =IF(OR(P12="N.A.",P12="",AF12=""),"N.A.",P12*AF12) -> 0.2 | AP12: =IF(OR(Q12="N.A.",Q12="",AG12=""),"N.A.",Q12*AG12) -> N.A. | AQ12: =IF(OR(R12="N.A.",R12="",AH12=""),"N.A.",R12*AH12) -> 1.25 | AR12: =IF(OR(S12="N.A.",S12="",AI12=""),"N.A.",S12*AI12) -> 0.75 | AS12: =IF(OR(T12="N.A.",T12="",AJ12=""),"N.A.",T12*AJ12) -> N.A. | AT12: =IF(AND(OR(AN12="",AN12="N.A."),OR(AO12="",AO12="N.A."),OR(AP12="",AP12="N.A."),OR(AQ12="",AQ12="N.A."),OR(AR12="",AR12="N.A."),OR(AS12="",AS12="N.A.")),"N.A.",MAX(AN12:AS12)) -> 1.75 | AU12: =IF(OR(V12="",V12="N.A.",AM12=""),"N.A.",V12*AM12) -> 0.3 | AV12: =IF(OR(AT12="N.A.",AU12="N.A."),"N.A.",ROUND(AT12*AU12,1)) -> 0.5 | AY12: =IF(AX12="","",VLOOKUP(AX12,Appoggio!$M$3:$N$7,2,0)) | BA12: =IF(AZ12="","",VLOOKUP(AZ12,Appoggio!$M$3:$N$7,2,0)) | BB12: =IF(AY12="",AT12,IF(AT12="N.A.","N.A.",AT12*AY12)) -> 1.75 | BC12: =IF(BA12="",AU12,IF(AU12="N.A.","N.A.",AU12*BA12)) -> 0.3 | BD12: =IF(OR(BB12="N.A.",BC12="N.A."),"N.A.",ROUND(BB12*BC12,1)) -> 0.5
C13: 7 | D13: PAC_D_07 | E13: Direzione Sanitaria | F13: Direttore Ingegneria Clinica | G13: PAC Area D - Immobilizzazioni / Ingegneria Clinica | H13: Rischio Finanziario | I13: Contabilità e reporting finanziario | K13: Errata gestione contabile degli incrementi di valore, manutenzioni straordinarie e cespiti modulari. | L13: Processi: - Intervento capitalizzabile trattato come costo o viceversa - Incremento non collegato al cespite padre - Piano di ammortamento dell'incremento non coerente con vita utile residua Persone: - Mancata indicazione tecnica da Ingegneria Clinica su natura e vita utile dell'intervento Fattori esterni: - Strumenti: - Anagrafica cespite priva di dettaglio separato per incremento | M13: Economiche: Errore nel valore del cespite e nel piano ammortamento Danno d'immagine: Rilievi PAC/revisori Salute e sicurezza: - Compliance normativa: Non conformità a principi contabili e procedure interne Gestionale - Operativo: Disallineamento tra configurazione tecnica e patrimoniale Ambiente: - | N13: Gli incrementi hanno impatto su capitale investito e ammortamenti; rischio significativo se non tracciati separatamente. | O13: 5 | P13: 2 | Q13: N.A. | R13: 5 | S13: 3 | T13: N.A. | U13: =IF(AND(OR(O13="",O13="N.A."),OR(P13="",P13="N.A."),OR(Q13="",Q13="N.A."),OR(R13="",R13="N.A."),OR(S13="",S13="N.A."),OR(T13="",T13="N.A.")),"N.A.",MAX(O13:T13)) -> 5 | V13: 3 | W13: =IF(OR(U13="N.A.",V13="",V13="N.A."),"N.A.",U13*V13) -> 15 | X13: Riclassifica contabile; caricamento incremento sul cespite padre; rimodulazione ammortamento se non prolunga vita utile. | Y13: 3 | Z13: 4 | AB13: 3 | AC13: 3 | AE13: =IF(Y13="","",VLOOKUP(Y13,Appoggio!$M$3:$N$7,2,0)) -> 0.25 | AF13: =IF(Z13="","",VLOOKUP(Z13,Appoggio!$M$3:$N$7,2,0)) -> 0.1 | AG13: =IF(AA13="","",VLOOKUP(AA13,Appoggio!$M$3:$N$7,2,0)) | AH13: =IF(AB13="","",VLOOKUP(AB13,Appoggio!$M$3:$N$7,2,0)) -> 0.25 | AI13: =IF(AC13="","",VLOOKUP(AC13,Appoggio!$M$3:$N$7,2,0)) -> 0.25 | AJ13: =IF(AD13="","",VLOOKUP(AD13,Appoggio!$M$3:$N$7,2,0)) | AK13: Valutazione tecnica preventiva; separata identificazione del valore iniziale e degli incrementi; comunicazione tra IC, Approvvigionamenti ed Economico-Finanziaria. | AL13: 3 | AM13: =IF(AL13="","",VLOOKUP(AL13,Appoggio!$M$3:$N$7,2,0)) -> 0.25 | AN13: =IF(OR(O13="N.A.",O13="",AE13=""),"N.A.",O13*AE13) -> 1.25 | AO13: =IF(OR(P13="N.A.",P13="",AF13=""),"N.A.",P13*AF13) -> 0.2 | AP13: =IF(OR(Q13="N.A.",Q13="",AG13=""),"N.A.",Q13*AG13) -> N.A. | AQ13: =IF(OR(R13="N.A.",R13="",AH13=""),"N.A.",R13*AH13) -> 1.25 | AR13: =IF(OR(S13="N.A.",S13="",AI13=""),"N.A.",S13*AI13) -> 0.75 | AS13: =IF(OR(T13="N.A.",T13="",AJ13=""),"N.A.",T13*AJ13) -> N.A. | AT13: =IF(AND(OR(AN13="",AN13="N.A."),OR(AO13="",AO13="N.A."),OR(AP13="",AP13="N.A."),OR(AQ13="",AQ13="N.A."),OR(AR13="",AR13="N.A."),OR(AS13="",AS13="N.A.")),"N.A.",MAX(AN13:AS13)) -> 1.25 | AU13: =IF(OR(V13="",V13="N.A.",AM13=""),"N.A.",V13*AM13) -> 0.75 | AV13: =IF(OR(AT13="N.A.",AU13="N.A."),"N.A.",ROUND(AT13*AU13,1)) -> 0.9 | AY13: =IF(AX13="","",VLOOKUP(AX13,Appoggio!$M$3:$N$7,2,0)) | BA13: =IF(AZ13="","",VLOOKUP(AZ13,Appoggio!$M$3:$N$7,2,0)) | BB13: =IF(AY13="",AT13,IF(AT13="N.A.","N.A.",AT13*AY13)) -> 1.25 | BC13: =IF(BA13="",AU13,IF(AU13="N.A.","N.A.",AU13*BA13)) -> 0.75 | BD13: =IF(OR(BB13="N.A.",BC13="N.A."),"N.A.",ROUND(BB13*BC13,1)) -> 0.9
C14: 8 | D14: PAC_D_08 | E14: Direzione Sanitaria | F14: Direttore Ingegneria Clinica | G14: PAC Area D - Immobilizzazioni / Ingegneria Clinica | H14: Rischio Operativo | I14: Attività, processi e procedure | K14: Mancata tracciabilità di trasferimenti, ubicazione e consegnatari/sub-consegnatari dei beni. | L14: Processi: - Richieste di trasferimento prive di inventari tecnici/patrimoniali - Mancata comunicazione del trasferimento ad Approvvigionamenti - Database tecnico e anagrafica cespiti non aggiornati Persone: - Mancato coordinamento tra consegnatario cedente, nuovo consegnatario e Ingegneria Clinica Fattori esterni: - Movimentazioni occasionali di apparecchiature complesse o ingombranti Strumenti: - | M14: Economiche: Costi per rintraccio, rettifica inventariale o danneggiamenti Danno d'immagine: Rilievi su responsabilità dei consegnatari Salute e sicurezza: Rischio indiretto per manutenzione o addestramento non correttamente associati al reparto Compliance normativa: Non conformità a obblighi inventariali Gestionale - Operativo: Difficoltà di ricognizione fisica e monitoraggio del bene Ambiente: - | N14: La tracciabilità del consegnatario è un controllo chiave del PAC e della gestione tecnica; impatto massimo gestionale/compliance. | O14: 3 | P14: 2 | Q14: 3 | R14: 5 | S14: 5 | T14: N.A. | U14: =IF(AND(OR(O14="",O14="N.A."),OR(P14="",P14="N.A."),OR(Q14="",Q14="N.A."),OR(R14="",R14="N.A."),OR(S14="",S14="N.A."),OR(T14="",T14="N.A.")),"N.A.",MAX(O14:T14)) -> 5 | V14: 3 | W14: =IF(OR(U14="N.A.",V14="",V14="N.A."),"N.A.",U14*V14) -> 15 | X14: Aggiornamento retroattivo ubicazione/consegnatario; riconciliazione inventari; formalizzazione del trasferimento e del relativo verbale. | Y14: 3 | Z14: 4 | AA14: 3 | AB14: 3 | AC14: 3 | AE14: =IF(Y14="","",VLOOKUP(Y14,Appoggio!$M$3:$N$7,2,0)) -> 0.25 | AF14: =IF(Z14="","",VLOOKUP(Z14,Appoggio!$M$3:$N$7,2,0)) -> 0.1 | AG14: =IF(AA14="","",VLOOKUP(AA14,Appoggio!$M$3:$N$7,2,0)) -> 0.25 | AH14: =IF(AB14="","",VLOOKUP(AB14,Appoggio!$M$3:$N$7,2,0)) -> 0.25 | AI14: =IF(AC14="","",VLOOKUP(AC14,Appoggio!$M$3:$N$7,2,0)) -> 0.25 | AJ14: =IF(AD14="","",VLOOKUP(AD14,Appoggio!$M$3:$N$7,2,0)) | AK14: Richiesta motivata con numeri inventario; verifica fattibilità e supervisione IC; comunicazione ad Approvvigionamenti e aggiornamento del database tecnico. | AL14: 4 | AM14: =IF(AL14="","",VLOOKUP(AL14,Appoggio!$M$3:$N$7,2,0)) -> 0.1 | AN14: =IF(OR(O14="N.A.",O14="",AE14=""),"N.A.",O14*AE14) -> 0.75 | AO14: =IF(OR(P14="N.A.",P14="",AF14=""),"N.A.",P14*AF14) -> 0.2 | AP14: =IF(OR(Q14="N.A.",Q14="",AG14=""),"N.A.",Q14*AG14) -> 0.75 | AQ14: =IF(OR(R14="N.A.",R14="",AH14=""),"N.A.",R14*AH14) -> 1.25 | AR14: =IF(OR(S14="N.A.",S14="",AI14=""),"N.A.",S14*AI14) -> 1.25 | AS14: =IF(OR(T14="N.A.",T14="",AJ14=""),"N.A.",T14*AJ14) -> N.A. | AT14: =IF(AND(OR(AN14="",AN14="N.A."),OR(AO14="",AO14="N.A."),OR(AP14="",AP14="N.A."),OR(AQ14="",AQ14="N.A."),OR(AR14="",AR14="N.A."),OR(AS14="",AS14="N.A.")),"N.A.",MAX(AN14:AS14)) -> 1.25 | AU14: =IF(OR(V14="",V14="N.A.",AM14=""),"N.A.",V14*AM14) -> 0.3 | AV14: =IF(OR(AT14="N.A.",AU14="N.A."),"N.A.",ROUND(AT14*AU14,1)) -> 0.4 | AY14: =IF(AX14="","",VLOOKUP(AX14,Appoggio!$M$3:$N$7,2,0)) | BA14: =IF(AZ14="","",VLOOKUP(AZ14,Appoggio!$M$3:$N$7,2,0)) | BB14: =IF(AY14="",AT14,IF(AT14="N.A.","N.A.",AT14*AY14)) -> 1.25 | BC14: =IF(BA14="",AU14,IF(AU14="N.A.","N.A.",AU14*BA14)) -> 0.3 | BD14: =IF(OR(BB14="N.A.",BC14="N.A."),"N.A.",ROUND(BB14*BC14,1)) -> 0.4
C15: 9 | D15: PAC_D_09 | E15: Direzione Sanitaria | F15: Direttore Ingegneria Clinica | G15: PAC Area D - Immobilizzazioni / Ingegneria Clinica | H15: Rischio Finanziario | I15: Contabilità e reporting finanziario | K15: Errata o tardiva dismissione dal libro cespiti e mancato allineamento con dismissione tecnica/fuori uso. | L15: Processi: - Proposta di fuori uso non trasmessa o non recepita - Mancata verifica di stato d'uso, valore residuo e ubicazione - Atto di dismissione non predisposto nei tempi Persone: - Mancata comunicazione tra Global Service, Ingegneria Clinica, UO assegnataria e Approvvigionamenti Fattori esterni: - Strumenti: - Software tecnico e libro cespiti non allineati | M15: Economiche: Valore patrimoniale non corretto, ammortamenti indebiti o mancato ricavo da alienazione Danno d'immagine: Rilievi PAC/revisori Salute e sicurezza: Rischio di permanenza in uso di bene non sicuro o non conveniente Compliance normativa: Non conformità al processo di dismissione Gestionale - Operativo: Inventario non aggiornato e scarsa attendibilità del parco tecnologico Ambiente: Smaltimento/RAEE non gestito correttamente | N15: Rischio importante per completezza del libro cespiti e adeguatezza del patrimonio tecnologico; mitigato da iter di proposta e atto periodico. | O15: 5 | P15: 2 | Q15: 5 | R15: 5 | S15: 5 | T15: 3 | U15: =IF(AND(OR(O15="",O15="N.A."),OR(P15="",P15="N.A."),OR(Q15="",Q15="N.A."),OR(R15="",R15="N.A."),OR(S15="",S15="N.A."),OR(T15="",T15="N.A.")),"N.A.",MAX(O15:T15)) -> 5 | V15: 3 | W15: =IF(OR(U15="N.A.",V15="",V15="N.A."),"N.A.",U15*V15) -> 15 | X15: Accantonamento del bene; proposta di fuori uso; aggiornamento software tecnico; atto di dismissione e allineamento contabilità generale-libro cespiti. | Y15: 3 | Z15: 4 | AA15: 4 | AB15: 3 | AC15: 3 | AD15: 3 | AE15: =IF(Y15="","",VLOOKUP(Y15,Appoggio!$M$3:$N$7,2,0)) -> 0.25 | AF15: =IF(Z15="","",VLOOKUP(Z15,Appoggio!$M$3:$N$7,2,0)) -> 0.1 | AG15: =IF(AA15="","",VLOOKUP(AA15,Appoggio!$M$3:$N$7,2,0)) -> 0.1 | AH15: =IF(AB15="","",VLOOKUP(AB15,Appoggio!$M$3:$N$7,2,0)) -> 0.25 | AI15: =IF(AC15="","",VLOOKUP(AC15,Appoggio!$M$3:$N$7,2,0)) -> 0.25 | AJ15: =IF(AD15="","",VLOOKUP(AD15,Appoggio!$M$3:$N$7,2,0)) -> 0.25 | AK15: Valutazione tecnica motivata da Global Service/IC; aggiornamento libro cespiti su proposta; predisposizione quadrimestrale dell'atto di dismissione e verifiche Economico-Finanziarie. | AL15: 4 | AM15: =IF(AL15="","",VLOOKUP(AL15,Appoggio!$M$3:$N$7,2,0)) -> 0.1 | AN15: =IF(OR(O15="N.A.",O15="",AE15=""),"N.A.",O15*AE15) -> 1.25 | AO15: =IF(OR(P15="N.A.",P15="",AF15=""),"N.A.",P15*AF15) -> 0.2 | AP15: =IF(OR(Q15="N.A.",Q15="",AG15=""),"N.A.",Q15*AG15) -> 0.5 | AQ15: =IF(OR(R15="N.A.",R15="",AH15=""),"N.A.",R15*AH15) -> 1.25 | AR15: =IF(OR(S15="N.A.",S15="",AI15=""),"N.A.",S15*AI15) -> 1.25 | AS15: =IF(OR(T15="N.A.",T15="",AJ15=""),"N.A.",T15*AJ15) -> 0.75 | AT15: =IF(AND(OR(AN15="",AN15="N.A."),OR(AO15="",AO15="N.A."),OR(AP15="",AP15="N.A."),OR(AQ15="",AQ15="N.A."),OR(AR15="",AR15="N.A."),OR(AS15="",AS15="N.A.")),"N.A.",MAX(AN15:AS15)) -> 1.25 | AU15: =IF(OR(V15="",V15="N.A.",AM15=""),"N.A.",V15*AM15) -> 0.3 | AV15: =IF(OR(AT15="N.A.",AU15="N.A."),"N.A.",ROUND(AT15*AU15,1)) -> 0.4 | AY15: =IF(AX15="","",VLOOKUP(AX15,Appoggio!$M$3:$N$7,2,0)) | BA15: =IF(AZ15="","",VLOOKUP(AZ15,Appoggio!$M$3:$N$7,2,0)) | BB15: =IF(AY15="",AT15,IF(AT15="N.A.","N.A.",AT15*AY15)) -> 1.25 | BC15: =IF(BA15="",AU15,IF(AU15="N.A.","N.A.",AU15*BA15)) -> 0.3 | BD15: =IF(OR(BB15="N.A.",BC15="N.A."),"N.A.",ROUND(BB15*BC15,1)) -> 0.4
C16: 10 | D16: PAC_D_10 | E16: Direzione Sanitaria | F16: Direttore Ingegneria Clinica | G16: PAC Area D - Immobilizzazioni / Ingegneria Clinica | H16: Rischio Operativo | I16: Attività, processi e procedure | K16: Inadeguate ricognizioni inventariali periodiche e quadrature tra inventario fisico, tecnico e contabile. | L16: Processi: - Ricognizioni inventariali non pianificate o incomplete - Assenza di riconciliazione periodica tra database tecnico e libro cespiti - KPI e report non analizzati Persone: - Mancata collaborazione delle UO consegnatarie Fattori esterni: - Strumenti: - Sistemi informativi non integrati o con dati non allineati | M16: Economiche: Differenze inventariali e valori patrimoniali non attendibili Danno d'immagine: Rilievi PAC e perdita di affidabilità del sistema di controllo interno Salute e sicurezza: Rischio indiretto per beni non rintracciabili o non manutenuti Compliance normativa: Non conformità alle procedure di inventario fisico periodico Gestionale - Operativo: Scarsa visibilità sul parco tecnologico e sulle decisioni di investimento Ambiente: - | N16: La ricognizione periodica è presidio trasversale del PAC Area D; rischio significativo per affidabilità delle immobilizzazioni. | O16: 5 | P16: 2 | Q16: 3 | R16: 5 | S16: 5 | T16: N.A. | U16: =IF(AND(OR(O16="",O16="N.A."),OR(P16="",P16="N.A."),OR(Q16="",Q16="N.A."),OR(R16="",R16="N.A."),OR(S16="",S16="N.A."),OR(T16="",T16="N.A.")),"N.A.",MAX(O16:T16)) -> 5 | V16: 3 | W16: =IF(OR(U16="N.A.",V16="",V16="N.A."),"N.A.",U16*V16) -> 15 | X16: Piano di riconciliazione straordinaria; rettifica dati tecnici e patrimoniali; coinvolgimento delle UO per conferma ubicazione/consegna. | Y16: 3 | Z16: 4 | AA16: 3 | AB16: 3 | AC16: 3 | AE16: =IF(Y16="","",VLOOKUP(Y16,Appoggio!$M$3:$N$7,2,0)) -> 0.25 | AF16: =IF(Z16="","",VLOOKUP(Z16,Appoggio!$M$3:$N$7,2,0)) -> 0.1 | AG16: =IF(AA16="","",VLOOKUP(AA16,Appoggio!$M$3:$N$7,2,0)) -> 0.25 | AH16: =IF(AB16="","",VLOOKUP(AB16,Appoggio!$M$3:$N$7,2,0)) -> 0.25 | AI16: =IF(AC16="","",VLOOKUP(AC16,Appoggio!$M$3:$N$7,2,0)) -> 0.25 | AJ16: =IF(AD16="","",VLOOKUP(AD16,Appoggio!$M$3:$N$7,2,0)) | AK16: Consultazione costante del database; estrapolazione di statistiche/indici; ricognizioni periodiche da Approvvigionamenti e controlli accessibili alle UO. | AL16: 3 | AM16: =IF(AL16="","",VLOOKUP(AL16,Appoggio!$M$3:$N$7,2,0)) -> 0.25 | AN16: =IF(OR(O16="N.A.",O16="",AE16=""),"N.A.",O16*AE16) -> 1.25 | AO16: =IF(OR(P16="N.A.",P16="",AF16=""),"N.A.",P16*AF16) -> 0.2 | AP16: =IF(OR(Q16="N.A.",Q16="",AG16=""),"N.A.",Q16*AG16) -> 0.75 | AQ16: =IF(OR(R16="N.A.",R16="",AH16=""),"N.A.",R16*AH16) -> 1.25 | AR16: =IF(OR(S16="N.A.",S16="",AI16=""),"N.A.",S16*AI16) -> 1.25 | AS16: =IF(OR(T16="N.A.",T16="",AJ16=""),"N.A.",T16*AJ16) -> N.A. | AT16: =IF(AND(OR(AN16="",AN16="N.A."),OR(AO16="",AO16="N.A."),OR(AP16="",AP16="N.A."),OR(AQ16="",AQ16="N.A."),OR(AR16="",AR16="N.A."),OR(AS16="",AS16="N.A.")),"N.A.",MAX(AN16:AS16)) -> 1.25 | AU16: =IF(OR(V16="",V16="N.A.",AM16=""),"N.A.",V16*AM16) -> 0.75 | AV16: =IF(OR(AT16="N.A.",AU16="N.A."),"N.A.",ROUND(AT16*AU16,1)) -> 0.9 | AY16: =IF(AX16="","",VLOOKUP(AX16,Appoggio!$M$3:$N$7,2,0)) | BA16: =IF(AZ16="","",VLOOKUP(AZ16,Appoggio!$M$3:$N$7,2,0)) | BB16: =IF(AY16="",AT16,IF(AT16="N.A.","N.A.",AT16*AY16)) -> 1.25 | BC16: =IF(BA16="",AU16,IF(AU16="N.A.","N.A.",AU16*BA16)) -> 0.75 | BD16: =IF(OR(BB16="N.A.",BC16="N.A."),"N.A.",ROUND(BB16*BC16,1)) -> 0.9
C17: 11 | D17: PAC_D_11 | E17: Direzione Sanitaria | F17: Direttore Ingegneria Clinica | G17: PAC Area D - Immobilizzazioni / Ingegneria Clinica | H17: Rischio Operativo | I17: Informativa e reporting | J17: Informativa interna ed esterna | K17: Incompleta conservazione della documentazione a supporto di ordini, DDT, collaudi, trasferimenti, incrementi e dismissioni. | L17: Processi: - Fascicoli tecnici/cartacei/elettronici incompleti - Documentazione cespiti non archiviata o non facilmente reperibile - Mancata tracciatura delle comunicazioni tra UO Persone: - Mancata trasmissione documenti da fornitore, Global Service, IC o Approvvigionamenti Fattori esterni: - Strumenti: - Archivi non strutturati o non riconciliati con anagrafica cespite | M17: Economiche: Costi e ritardi per ricostruzioni documentali o contenziosi Danno d'immagine: Rilievi di audit e controlli interni Salute e sicurezza: Difficoltà nel dimostrare collaudo, addestramento e manutenzione Compliance normativa: Non conformità a requisiti documentali PAC e ISO Gestionale - Operativo: Perdita di informazioni critiche per il ciclo di vita del bene Ambiente: - | N17: La documentazione è evidenza del controllo; la sua incompletezza compromette l'assurance PAC pur in presenza di attività svolte. | O17: 3 | P17: 2 | Q17: 3 | R17: 5 | S17: 5 | T17: N.A. | U17: =IF(AND(OR(O17="",O17="N.A."),OR(P17="",P17="N.A."),OR(Q17="",Q17="N.A."),OR(R17="",R17="N.A."),OR(S17="",S17="N.A."),OR(T17="",T17="N.A.")),"N.A.",MAX(O17:T17)) -> 5 | V17: 3 | W17: =IF(OR(U17="N.A.",V17="",V17="N.A."),"N.A.",U17*V17) -> 15 | X17: Recupero documenti mancanti; ricostruzione del fascicolo; archiviazione integrativa e note di riconciliazione con anagrafica cespite. | Y17: 3 | Z17: 4 | AA17: 3 | AB17: 3 | AC17: 3 | AE17: =IF(Y17="","",VLOOKUP(Y17,Appoggio!$M$3:$N$7,2,0)) -> 0.25 | AF17: =IF(Z17="","",VLOOKUP(Z17,Appoggio!$M$3:$N$7,2,0)) -> 0.1 | AG17: =IF(AA17="","",VLOOKUP(AA17,Appoggio!$M$3:$N$7,2,0)) -> 0.25 | AH17: =IF(AB17="","",VLOOKUP(AB17,Appoggio!$M$3:$N$7,2,0)) -> 0.25 | AI17: =IF(AC17="","",VLOOKUP(AC17,Appoggio!$M$3:$N$7,2,0)) -> 0.25 | AJ17: =IF(AD17="","",VLOOKUP(AD17,Appoggio!$M$3:$N$7,2,0)) | AK17: Archiviazione illimitata Global Service per collaudo/dismissione; conservazione Approvvigionamenti di dati libro cespiti, ordini, DDT, collaudi, trasferimenti e dismissioni. | AL17: 4 | AM17: =IF(AL17="","",VLOOKUP(AL17,Appoggio!$M$3:$N$7,2,0)) -> 0.1 | AN17: =IF(OR(O17="N.A.",O17="",AE17=""),"N.A.",O17*AE17) -> 0.75 | AO17: =IF(OR(P17="N.A.",P17="",AF17=""),"N.A.",P17*AF17) -> 0.2 | AP17: =IF(OR(Q17="N.A.",Q17="",AG17=""),"N.A.",Q17*AG17) -> 0.75 | AQ17: =IF(OR(R17="N.A.",R17="",AH17=""),"N.A.",R17*AH17) -> 1.25 | AR17: =IF(OR(S17="N.A.",S17="",AI17=""),"N.A.",S17*AI17) -> 1.25 | AS17: =IF(OR(T17="N.A.",T17="",AJ17=""),"N.A.",T17*AJ17) -> N.A. | AT17: =IF(AND(OR(AN17="",AN17="N.A."),OR(AO17="",AO17="N.A."),OR(AP17="",AP17="N.A."),OR(AQ17="",AQ17="N.A."),OR(AR17="",AR17="N.A."),OR(AS17="",AS17="N.A.")),"N.A.",MAX(AN17:AS17)) -> 1.25 | AU17: =IF(OR(V17="",V17="N.A.",AM17=""),"N.A.",V17*AM17) -> 0.3 | AV17: =IF(OR(AT17="N.A.",AU17="N.A."),"N.A.",ROUND(AT17*AU17,1)) -> 0.4 | AY17: =IF(AX17="","",VLOOKUP(AX17,Appoggio!$M$3:$N$7,2,0)) | BA17: =IF(AZ17="","",VLOOKUP(AZ17,Appoggio!$M$3:$N$7,2,0)) | BB17: =IF(AY17="",AT17,IF(AT17="N.A.","N.A.",AT17*AY17)) -> 1.25 | BC17: =IF(BA17="",AU17,IF(AU17="N.A.","N.A.",AU17*BA17)) -> 0.3 | BD17: =IF(OR(BB17="N.A.",BC17="N.A."),"N.A.",ROUND(BB17*BC17,1)) -> 0.4
C18: 12 | D18: PAC_D_12 | E18: Direzione Sanitaria | F18: Direttore Ingegneria Clinica | G18: PAC Area D - Immobilizzazioni / Ingegneria Clinica | H18: Rischio Operativo | I18: Attività, processi e procedure | K18: Ruoli, responsabilità e flussi informativi non coerenti con la matrice di responsabilità della procedura. | L18: Processi: - Mancata applicazione della matrice RACI - Passaggi tra Ufficio ordinatore, Approvvigionamenti, Magazzino, Economico-Finanziaria, IC, UO, Global Service e fornitore non tracciati Persone: - Ambiguità di ownership o sostituzioni di personale non formalizzate Fattori esterni: - Strumenti: - Workflow informali non supportati da sistemi o check-list | M18: Economiche: Extra costi per ritardi, duplicazioni o rettifiche Danno d'immagine: Rilievi sul sistema di controllo interno Salute e sicurezza: Rischio indiretto in caso di collaudo/manutenzione non presidiati Compliance normativa: Non conformità a procedure interne e PAC Gestionale - Operativo: Ritardi operativi, attività non eseguite o non documentate Ambiente: - | N18: Il disallineamento dei ruoli riduce l'efficacia dei controlli di primo livello; impatto massimo gestionale/compliance. | O18: 3 | P18: 2 | Q18: 3 | R18: 5 | S18: 5 | T18: N.A. | U18: =IF(AND(OR(O18="",O18="N.A."),OR(P18="",P18="N.A."),OR(Q18="",Q18="N.A."),OR(R18="",R18="N.A."),OR(S18="",S18="N.A."),OR(T18="",T18="N.A.")),"N.A.",MAX(O18:T18)) -> 5 | V18: 3 | W18: =IF(OR(U18="N.A.",V18="",V18="N.A."),"N.A.",U18*V18) -> 15 | X18: Riunione di riallineamento tra attori; formalizzazione responsabilità e recupero attività/documenti pendenti. | Y18: 3 | Z18: 4 | AA18: 3 | AB18: 3 | AC18: 3 | AE18: =IF(Y18="","",VLOOKUP(Y18,Appoggio!$M$3:$N$7,2,0)) -> 0.25 | AF18: =IF(Z18="","",VLOOKUP(Z18,Appoggio!$M$3:$N$7,2,0)) -> 0.1 | AG18: =IF(AA18="","",VLOOKUP(AA18,Appoggio!$M$3:$N$7,2,0)) -> 0.25 | AH18: =IF(AB18="","",VLOOKUP(AB18,Appoggio!$M$3:$N$7,2,0)) -> 0.25 | AI18: =IF(AC18="","",VLOOKUP(AC18,Appoggio!$M$3:$N$7,2,0)) -> 0.25 | AJ18: =IF(AD18="","",VLOOKUP(AD18,Appoggio!$M$3:$N$7,2,0)) | AK18: Matrice di responsabilità PO 595; flussi informativi previsti per collaudo, trasferimento, dismissione e conservazione documentale. | AL18: 4 | AM18: =IF(AL18="","",VLOOKUP(AL18,Appoggio!$M$3:$N$7,2,0)) -> 0.1 | AN18: =IF(OR(O18="N.A.",O18="",AE18=""),"N.A.",O18*AE18) -> 0.75 | AO18: =IF(OR(P18="N.A.",P18="",AF18=""),"N.A.",P18*AF18) -> 0.2 | AP18: =IF(OR(Q18="N.A.",Q18="",AG18=""),"N.A.",Q18*AG18) -> 0.75 | AQ18: =IF(OR(R18="N.A.",R18="",AH18=""),"N.A.",R18*AH18) -> 1.25 | AR18: =IF(OR(S18="N.A.",S18="",AI18=""),"N.A.",S18*AI18) -> 1.25 | AS18: =IF(OR(T18="N.A.",T18="",AJ18=""),"N.A.",T18*AJ18) -> N.A. | AT18: =IF(AND(OR(AN18="",AN18="N.A."),OR(AO18="",AO18="N.A."),OR(AP18="",AP18="N.A."),OR(AQ18="",AQ18="N.A."),OR(AR18="",AR18="N.A."),OR(AS18="",AS18="N.A.")),"N.A.",MAX(AN18:AS18)) -> 1.25 | AU18: =IF(OR(V18="",V18="N.A.",AM18=""),"N.A.",V18*AM18) -> 0.3 | AV18: =IF(OR(AT18="N.A.",AU18="N.A."),"N.A.",ROUND(AT18*AU18,1)) -> 0.4 | AY18: =IF(AX18="","",VLOOKUP(AX18,Appoggio!$M$3:$N$7,2,0)) | BA18: =IF(AZ18="","",VLOOKUP(AZ18,Appoggio!$M$3:$N$7,2,0)) | BB18: =IF(AY18="",AT18,IF(AT18="N.A.","N.A.",AT18*AY18)) -> 1.25 | BC18: =IF(BA18="",AU18,IF(AU18="N.A.","N.A.",AU18*BA18)) -> 0.3 | BD18: =IF(OR(BB18="N.A.",BC18="N.A."),"N.A.",ROUND(BB18*BC18,1)) -> 0.4
C19: 13 | D19: PAC_D_13 | E19: Direzione Sanitaria | F19: Direttore Ingegneria Clinica | G19: PAC Area D - Immobilizzazioni / Ingegneria Clinica | H19: Rischio Operativo | I19: Informativa e reporting | J19: Misurazione delle performance | K19: Disallineamento tra inventario tecnico del Global Service e libro cespiti/inventario patrimoniale NFS. | L19: Processi: - Aggiornamenti tecnici non comunicati all'inventario patrimoniale - Cespite patrimoniale non abbinato all'etichetta tecnica - Dati su stato, ubicazione e piani manutentivi non riconciliati Persone: - Mancato controllo periodico incrociato IC/Approvvigionamenti Fattori esterni: - Strumenti: - Database separati con codifiche o campi non omogenei | M19: Economiche: Valori patrimoniali o consistenza inventariale non allineati Danno d'immagine: Rilievi PAC e perdita di affidabilità dei report Salute e sicurezza: Piano manutentivo non associato correttamente al bene Compliance normativa: Non conformità a tracciabilità e controlli inventariali Gestionale - Operativo: Report e decisioni su sostituzioni/dismissioni basati su dati non aggiornati Ambiente: - | N19: Rischio trasversale tra gestione tecnica e patrimoniale; impatto significativo su reporting, manutenzione e controlli periodici. | O19: 5 | P19: 2 | Q19: 3 | R19: 5 | S19: 5 | T19: N.A. | U19: =IF(AND(OR(O19="",O19="N.A."),OR(P19="",P19="N.A."),OR(Q19="",Q19="N.A."),OR(R19="",R19="N.A."),OR(S19="",S19="N.A."),OR(T19="",T19="N.A.")),"N.A.",MAX(O19:T19)) -> 5 | V19: 3 | W19: =IF(OR(U19="N.A.",V19="",V19="N.A."),"N.A.",U19*V19) -> 15 | X19: Riconciliazione puntuale dei record; correzione etichette/codici; allineamento stato, ubicazione e dati tecnici/patrimoniali. | Y19: 3 | Z19: 4 | AA19: 3 | AB19: 3 | AC19: 3 | AE19: =IF(Y19="","",VLOOKUP(Y19,Appoggio!$M$3:$N$7,2,0)) -> 0.25 | AF19: =IF(Z19="","",VLOOKUP(Z19,Appoggio!$M$3:$N$7,2,0)) -> 0.1 | AG19: =IF(AA19="","",VLOOKUP(AA19,Appoggio!$M$3:$N$7,2,0)) -> 0.25 | AH19: =IF(AB19="","",VLOOKUP(AB19,Appoggio!$M$3:$N$7,2,0)) -> 0.25 | AI19: =IF(AC19="","",VLOOKUP(AC19,Appoggio!$M$3:$N$7,2,0)) -> 0.25 | AJ19: =IF(AD19="","",VLOOKUP(AD19,Appoggio!$M$3:$N$7,2,0)) | AK19: Doppia inventariazione; consultazione database; relazioni periodiche e controlli di coerenza tra fascicolo tecnico e scheda cespite. | AL19: 3 | AM19: =IF(AL19="","",VLOOKUP(AL19,Appoggio!$M$3:$N$7,2,0)) -> 0.25 | AN19: =IF(OR(O19="N.A.",O19="",AE19=""),"N.A.",O19*AE19) -> 1.25 | AO19: =IF(OR(P19="N.A.",P19="",AF19=""),"N.A.",P19*AF19) -> 0.2 | AP19: =IF(OR(Q19="N.A.",Q19="",AG19=""),"N.A.",Q19*AG19) -> 0.75 | AQ19: =IF(OR(R19="N.A.",R19="",AH19=""),"N.A.",R19*AH19) -> 1.25 | AR19: =IF(OR(S19="N.A.",S19="",AI19=""),"N.A.",S19*AI19) -> 1.25 | AS19: =IF(OR(T19="N.A.",T19="",AJ19=""),"N.A.",T19*AJ19) -> N.A. | AT19: =IF(AND(OR(AN19="",AN19="N.A."),OR(AO19="",AO19="N.A."),OR(AP19="",AP19="N.A."),OR(AQ19="",AQ19="N.A."),OR(AR19="",AR19="N.A."),OR(AS19="",AS19="N.A.")),"N.A.",MAX(AN19:AS19)) -> 1.25 | AU19: =IF(OR(V19="",V19="N.A.",AM19=""),"N.A.",V19*AM19) -> 0.75 | AV19: =IF(OR(AT19="N.A.",AU19="N.A."),"N.A.",ROUND(AT19*AU19,1)) -> 0.9 | AY19: =IF(AX19="","",VLOOKUP(AX19,Appoggio!$M$3:$N$7,2,0)) | BA19: =IF(AZ19="","",VLOOKUP(AZ19,Appoggio!$M$3:$N$7,2,0)) | BB19: =IF(AY19="",AT19,IF(AT19="N.A.","N.A.",AT19*AY19)) -> 1.25 | BC19: =IF(BA19="",AU19,IF(AU19="N.A.","N.A.",AU19*BA19)) -> 0.75 | BD19: =IF(OR(BB19="N.A.",BC19="N.A."),"N.A.",ROUND(BB19*BC19,1)) -> 0.9
C20: 14 | D20: PAC_D_14 | E20: Direzione Sanitaria | F20: Direttore Ingegneria Clinica | G20: PAC Area D - Immobilizzazioni / Ingegneria Clinica | H20: Rischio Operativo | I20: Attività, processi e procedure | K20: Accettazione di donazioni di apparecchiature senza adeguata valutazione di strumentalità, conformità e costi/benefici. | L20: Processi: - Parere tecnico IC incompleto o tardivo - Costi accessori, installazione, messa a norma, manutenzione e riparazione non valutati - Documentazione sul valore del bene non adeguata Persone: - Pressioni organizzative per accettazione rapida del bene Fattori esterni: - Donazioni di tecnologie non recenti o non pienamente conformi Strumenti: - | M20: Economiche: Costi non preventivati di installazione, adeguamento, manutenzione o smaltimento Danno d'immagine: Criticità verso donante, UO o stakeholder se il bene non è utilizzabile Salute e sicurezza: Rischio da apparecchiatura non conforme o non adatta al contesto Compliance normativa: Non conformità a requisiti di sicurezza, salute sul lavoro e iter deliberativo Gestionale - Operativo: Inserimento di tecnologia non coerente con fabbisogni o sostenibilità Ambiente: - | N20: Le donazioni possono generare rischi tecnici e patrimoniali se non valutate prima dell'accettazione; impatto salute/compliance significativo. | O20: 3 | P20: 2 | Q20: 5 | R20: 5 | S20: 5 | T20: 3 | U20: =IF(AND(OR(O20="",O20="N.A."),OR(P20="",P20="N.A."),OR(Q20="",Q20="N.A."),OR(R20="",R20="N.A."),OR(S20="",S20="N.A."),OR(T20="",T20="N.A.")),"N.A.",MAX(O20:T20)) -> 5 | V20: 3 | W20: =IF(OR(U20="N.A.",V20="",V20="N.A."),"N.A.",U20*V20) -> 15 | X20: Sospensione dell'accettazione o non accettazione motivata; richiesta integrazioni documentali; valutazione messa a norma/costi e collaudo. | Y20: 3 | Z20: 4 | AA20: 4 | AB20: 3 | AC20: 3 | AD20: 3 | AE20: =IF(Y20="","",VLOOKUP(Y20,Appoggio!$M$3:$N$7,2,0)) -> 0.25 | AF20: =IF(Z20="","",VLOOKUP(Z20,Appoggio!$M$3:$N$7,2,0)) -> 0.1 | AG20: =IF(AA20="","",VLOOKUP(AA20,Appoggio!$M$3:$N$7,2,0)) -> 0.1 | AH20: =IF(AB20="","",VLOOKUP(AB20,Appoggio!$M$3:$N$7,2,0)) -> 0.25 | AI20: =IF(AC20="","",VLOOKUP(AC20,Appoggio!$M$3:$N$7,2,0)) -> 0.25 | AJ20: =IF(AD20="","",VLOOKUP(AD20,Appoggio!$M$3:$N$7,2,0)) -> 0.25 | AK20: Parere Ingegneria Clinica su strumentalità e costi/benefici; verifica conformità normativa, spese di consegna/installazione/esercizio/manutenzione; atto deliberativo Approvvigionamenti. | AL20: 4 | AM20: =IF(AL20="","",VLOOKUP(AL20,Appoggio!$M$3:$N$7,2,0)) -> 0.1 | AN20: =IF(OR(O20="N.A.",O20="",AE20=""),"N.A.",O20*AE20) -> 0.75 | AO20: =IF(OR(P20="N.A.",P20="",AF20=""),"N.A.",P20*AF20) -> 0.2 | AP20: =IF(OR(Q20="N.A.",Q20="",AG20=""),"N.A.",Q20*AG20) -> 0.5 | AQ20: =IF(OR(R20="N.A.",R20="",AH20=""),"N.A.",R20*AH20) -> 1.25 | AR20: =IF(OR(S20="N.A.",S20="",AI20=""),"N.A.",S20*AI20) -> 1.25 | AS20: =IF(OR(T20="N.A.",T20="",AJ20=""),"N.A.",T20*AJ20) -> 0.75 | AT20: =IF(AND(OR(AN20="",AN20="N.A."),OR(AO20="",AO20="N.A."),OR(AP20="",AP20="N.A."),OR(AQ20="",AQ20="N.A."),OR(AR20="",AR20="N.A."),OR(AS20="",AS20="N.A.")),"N.A.",MAX(AN20:AS20)) -> 1.25 | AU20: =IF(OR(V20="",V20="N.A.",AM20=""),"N.A.",V20*AM20) -> 0.3 | AV20: =IF(OR(AT20="N.A.",AU20="N.A."),"N.A.",ROUND(AT20*AU20,1)) -> 0.4 | AY20: =IF(AX20="","",VLOOKUP(AX20,Appoggio!$M$3:$N$7,2,0)) | BA20: =IF(AZ20="","",VLOOKUP(AZ20,Appoggio!$M$3:$N$7,2,0)) | BB20: =IF(AY20="",AT20,IF(AT20="N.A.","N.A.",AT20*AY20)) -> 1.25 | BC20: =IF(BA20="",AU20,IF(AU20="N.A.","N.A.",AU20*BA20)) -> 0.3 | BD20: =IF(OR(BB20="N.A.",BC20="N.A."),"N.A.",ROUND(BB20*BC20,1)) -> 0.4
C21: 15 | D21: PAC_D_15 | E21: Direzione Sanitaria | F21: Direttore Ingegneria Clinica | G21: PAC Area D - Immobilizzazioni / Ingegneria Clinica | H21: Rischio Esterno | I21: Gestione Terze Parti | K21: Inadeguato monitoraggio dei contratti di manutenzione e dei livelli di servizio con impatto sul ciclo immobilizzazioni. | L21: Processi: - KPI manutentivi e contrattuali non monitorati o non formalizzati - Relazioni periodiche non ricevute o non analizzate - Ritardi del fornitore non contestati Persone: - Mancata escalation verso funzioni competenti Fattori esterni: - Global Service o ditte specialistiche con performance non coerente con capitolato Strumenti: - | M21: Economiche: Extra costi per guasti, fermo macchina, sostituzioni o penali non applicate Danno d'immagine: Disservizi verso reparti e rilievi su governance contrattuale Salute e sicurezza: Aumento del rischio se beni critici non sono manutenuti Compliance normativa: Inadempienze contrattuali non gestite Gestionale - Operativo: Interruzioni operative e dati manutentivi non affidabili Ambiente: - | N21: Il contratto di manutenzione è controllo chiave per conservazione del valore e sicurezza del patrimonio tecnologico; impatto gestione/sicurezza significativo. | O21: 3 | P21: 2 | Q21: 5 | R21: 5 | S21: 5 | T21: 3 | U21: =IF(AND(OR(O21="",O21="N.A."),OR(P21="",P21="N.A."),OR(Q21="",Q21="N.A."),OR(R21="",R21="N.A."),OR(S21="",S21="N.A."),OR(T21="",T21="N.A.")),"N.A.",MAX(O21:T21)) -> 5 | V21: 3 | W21: =IF(OR(U21="N.A.",V21="",V21="N.A."),"N.A.",U21*V21) -> 15 | X21: Solleciti e contestazioni; attivazione penali/azioni contrattuali se previste; affidamento intervento alternativo in urgenza. | Y21: 3 | Z21: 4 | AA21: 4 | AB21: 3 | AC21: 3 | AD21: 4 | AE21: =IF(Y21="","",VLOOKUP(Y21,Appoggio!$M$3:$N$7,2,0)) -> 0.25 | AF21: =IF(Z21="","",VLOOKUP(Z21,Appoggio!$M$3:$N$7,2,0)) -> 0.1 | AG21: =IF(AA21="","",VLOOKUP(AA21,Appoggio!$M$3:$N$7,2,0)) -> 0.1 | AH21: =IF(AB21="","",VLOOKUP(AB21,Appoggio!$M$3:$N$7,2,0)) -> 0.25 | AI21: =IF(AC21="","",VLOOKUP(AC21,Appoggio!$M$3:$N$7,2,0)) -> 0.25 | AJ21: =IF(AD21="","",VLOOKUP(AD21,Appoggio!$M$3:$N$7,2,0)) -> 0.1 | AK21: Monitoraggio gestionale di tempi intervento/risoluzione e cronoprogrammi; dashboard contrattuali; relazione periodica del gestore. | AL21: 4 | AM21: =IF(AL21="","",VLOOKUP(AL21,Appoggio!$M$3:$N$7,2,0)) -> 0.1 | AN21: =IF(OR(O21="N.A.",O21="",AE21=""),"N.A.",O21*AE21) -> 0.75 | AO21: =IF(OR(P21="N.A.",P21="",AF21=""),"N.A.",P21*AF21) -> 0.2 | AP21: =IF(OR(Q21="N.A.",Q21="",AG21=""),"N.A.",Q21*AG21) -> 0.5 | AQ21: =IF(OR(R21="N.A.",R21="",AH21=""),"N.A.",R21*AH21) -> 1.25 | AR21: =IF(OR(S21="N.A.",S21="",AI21=""),"N.A.",S21*AI21) -> 1.25 | AS21: =IF(OR(T21="N.A.",T21="",AJ21=""),"N.A.",T21*AJ21) -> 0.3 | AT21: =IF(AND(OR(AN21="",AN21="N.A."),OR(AO21="",AO21="N.A."),OR(AP21="",AP21="N.A."),OR(AQ21="",AQ21="N.A."),OR(AR21="",AR21="N.A."),OR(AS21="",AS21="N.A.")),"N.A.",MAX(AN21:AS21)) -> 1.25 | AU21: =IF(OR(V21="",V21="N.A.",AM21=""),"N.A.",V21*AM21) -> 0.3 | AV21: =IF(OR(AT21="N.A.",AU21="N.A."),"N.A.",ROUND(AT21*AU21,1)) -> 0.4 | AY21: =IF(AX21="","",VLOOKUP(AX21,Appoggio!$M$3:$N$7,2,0)) | BA21: =IF(AZ21="","",VLOOKUP(AZ21,Appoggio!$M$3:$N$7,2,0)) | BB21: =IF(AY21="",AT21,IF(AT21="N.A.","N.A.",AT21*AY21)) -> 1.25 | BC21: =IF(BA21="",AU21,IF(AU21="N.A.","N.A.",AU21*BA21)) -> 0.3 | BD21: =IF(OR(BB21="N.A.",BC21="N.A."),"N.A.",ROUND(BB21*BC21,1)) -> 0.4

Sheet Rischi per aree PAC
B1: PAC (Percorso Attuativo della Certificabilità) | D1: ESTERNI | F1: Contesto socio-economico nazionale e regionale | G1: Contabilità e reporting finanziario | H1: Comunicazione e relazioni istituzionali | I1: Gestione apparecchiature sanitarie | J1: Anticorruzione | L1: N.A.
D2: FINANZIARI | F2: Evoluzione del contesto normativo | G2: Erariale patrimoniale | H2: Governance | I2: Gestione farmaci e dispositivi medici | J2: Codice etico
D3: STRATEGICI | F3: Gestione Terze Parti | G3: Fiscale | H3: Immagine/Reputazione | J3: Contrattualistica e controversie legali
D4: OPERATIVI | F4: Illeciti esterni | G4: Liquidità e credito | H4: Investimenti e patrimonio | J4: Normativa (regionale, nazionale, comunitaria)
D5: COMPLIANCE | F5: Sicurezza informatica | G5: Tassi d’interesse | H5: Pianificazione strategica | J5: Regolamenti interni
H6: Sistema di Controllo Interno | J6: Sicurezza delle informazioni e tutela privacy
G17: ESTERNI
G18: FINANZIARI
G19: STRATEGICI
G20: OPERATIVI
G21: COMPLIANCE

Sheet Risk Guide
C2: Risk Guide
C6: # Rischio | D6: Numero progressivo associato a ciascuno scenario di rischio
C8: ID Rischio | D8: Codice univoco associato a ciascuno scenario di rischio rilevato, contenente la sigla del Processo, la Categoria di Rischio e il numero progressivo associato a ciascuno scenario di rischio
C10: Direzione | D10: Area aziendale responsabile della gestione del rischio identificato
C12: Risk Owner | D12: Responsabile dell'Area aziendale che gestisce il rischio, ne comprende l’entità, decide la misura di trattamento (tollerarlo, mitigarlo, esternalizzarlo, eliminarlo) e guida la sua implementazione
C14: Processo | D14: Processo di riferimento, individuato sulla base del Process Model specifico per la struttura
C16: Categoria Rischio Liv. 1 | D16: Raggruppamento dei rischi secondo categorie omogenee per natura, caratteristiche o manifestazione. Le categorie sono identificate e definite nel Risk Model.
C18: Categoria Rischio Liv. 2 | D18: Sotto-categorie di rischio identificate nel Risk Model
C20: Categoria Rischio Liv. 2 | D20: Categoria di rischio di 3° livello identificate nel Risk Model
C22: Scenario di rischio | D22: Descrizione del rischio rilevato. Rischio: Evento probabile ma non certo che può portare ad uno scostamento (negativo) dagli obiettivi o dal valore atteso
C24: Principali cause del rischio | D24: Principali cause che possono scatenare il rischio rilevato
C26: Principali conseguenze del rischio | D26: Principali conseguenze che possono derivare dal rischio
C28: Valutazione del Rischio | D28: Informazioni a supporto del processo di valutazione
... C40: Valutazione Rischio Residuo to-be | D40: Valore del rischio residuo previsto, considerata l'implementazione delle azioni di mitigazione e miglioramento

Sheet Risk Model
C2: Risk Model
C5: Categoria di Rischio Liv. 1 | D5: Categoria di Rischio Liv. 2 | E5: Descrizione | F5: Categoria di Rischio Liv. 3 | G5: Descrizione
C6: CLINICO-SANITARI (Rischi derivanti da eventi che possono prolungare il periodo di degenza, il peggioramento delle condizioni di salute o la morte del paziente) | D6: Anestesiologico | E6: Durante l’induzione dell’anestesia o in fase di rianimazione, somministrazione di farmaci/dosaggi sbagliati o esecuzione di procedure/manovre errate che possono causare reazioni avverse (es. lesioni, reazioni allergiche).
D7: Assistenziale | E7: Ogni inesattezza, incompletezza od omissione commessa nell’esecuzione di procedure/manovre clinico-assistenziali mediche e infermieristiche (es. posizionamento catetere/drenaggio, preparazione intervento, mobilizzazione e posizionamento nel posto letto, sorveglianza post-operatoria) che possono causare aventi avversi.
D8: Atti di autolesione e tentativi di suicidio | E8: Possibilità del paziente di provocarsi dolore o lesioni superficiali intenzionali finalizzati all’autolesionismo o alla morte. Atti di autolesione non intenzionali.
D9: Caduta | E9: Improvviso, non intenzionale, inaspettato spostamento verso il basso dalla posizione ortostatica o assisa o clinostatica del paziente, ospite o caregiver. La testimonianza delle cadute è basata sul ricordo del paziente e/o la descrizione della caduta da parte dei testimoni. Qui sono incluse i pazienti che dormendo sulla sedia cadono per terra, i pazienti ritrovati sul pavimento e le cadute avvenute nonostante il supporto.
D10: Chirurgico | E10: Corpi estranei nel focolaio chirurgico, intervento su parte o lato del corpo sbagliata, esecuzione chirurgica impropria, chirurgia non necessaria, utilizzo di materiale chirurgico difettoso, gestione non corretta del paziente chirurgico.
D11: Diagnostico | E11: Esami o procedure diagnostiche non eseguite, programmate ma non eseguite, eseguite in modo inadeguato o scorretto o con materiali inadeguati, eseguite tardivamente, non appropriate. L’area include le procedure invasive e non invasive a scopo diagnostico.
D12: Gestione / redazione documenti | E12: Inesattezza, incompletezza, scarsa leggibilità, incomprensione degli acronimi/abbreviazioni della documentazione utilizzata nei processi clinico-assistenziali (es. consenso informato, cartella clinica, cartella infermieristica, referti, lettera dimissioni). Documentazione sanitaria che non rappresenta esaustivamente il percorso del paziente (inclusi eventuali trasferimenti) o che non contiene informazioni per garantire la continuità delle cure.
D13: Identificazione del paziente | E13: Possibilità di scambiare dati anagrafici di pazienti diversi oppure di eseguire procedure diagnostico-terapeutiche su un paziente ma prescritte a pazienti diversi.
D14: Infezione correlata all'assistenza | E14: Possibilità di acquisire infezioni in ogni ambito assistenziale, incluso gli ospedali per acuti, il day-hospital/day-surgery, le strutture di lungodegenza, gli ambulatori, l’assistenza domiciliare, le strutture residenziali territoriali.
D15: Ostetrico e neonatale, inclusi i trigger | E15: Ogni inesattezza, incompletezza od omissione che può verificarsi nelle fasi di gestione dei percorsi di cura materno-neonatali nelle fasi di gravidanza, parto e puerperio.
D16: Prevenzione | E16: Ogni inesattezza, incompletezza od omissione che può verificarsi nelle campagne di promozione della salute individuale e collettiva (es. screening, iniziative di sensibilizzazione) o nelle attività finalizzate alla riduzione dei fattori di rischio delle malattie (es. vaccini, profilassi antibiotica).
D17: Sperimentazioni cliniche | E17: Violazione dei diritti, della sicurezza e del benessere dei soggetti coinvolti nelle sperimentazioni cliniche. Inesattezza/incompletezza del protocollo di sperimentazione. Mancata indipendenza del Comitato Etico.
D18: Terapeutico | E18: Ogni evento avverso, indesiderabile, non intenzionale, prevenibile che può causare o portare ad un uso inappropriato del farmaco o ad un pericolo per il paziente: errore di prescrizione, di trasmissione della prescrizione, etichettatura, confezionamento o denominazione, allestimento, dispensazione, distribuzione, somministrazione, educazione, monitoraggio ed uso.
D19: Trasfusionale | E19: Ogni inesattezza, incompletezza od omissione che può verificarsi nelle fasi del processo trasfusionale: prelievo del campione, richiesta di emocomponenti, accettazione-registrazione-assegnazione presso il Servizio Trasfusionale e trasfusione presso la struttura sanitaria.
C20: ESTERNI (Rischi derivanti da eventi e cambiamenti nell'ambiente e nel contesto in cui l'azienda opera) | D20: Contesto socio-economico nazionale e regionale | E20: Dinamiche macroeconomiche o di contesto socio-politico che generano ripercussioni negative sullo scenario in cui l’Azienda opera.
D21: Eventi naturali o accidentale | E21: Eventi catastrofali o calamitosi di tipo naturale (es. alluvioni, inondazioni, terremoti) o atto involontario che genera conseguenze negative sull’operatività aziendale.
D22: Evoluzione del contesto normativo | E22: Variazioni/cambiamenti sfavorevoli delle norme/regolamenti regionali e nazionali vigenti con ripercussioni sulle attività e sulla struttura organizzativa.
D23: Gestione Terze Parti | E23: Difformità qualitative, ritardi nei tempi di fornitura e ogni altro tipo di inadempimento contrattuale generato dai fornitori di beni e servizi. Informazioni inesatte, ritardi e ogni altra forma di scarsa collaborazione di soggetti coinvolti nei progetti di partnership.
D24: Illeciti esterni | E24: Atto/comportamento illecito doloso o colposo commesso da terzi o che coinvolgono terze parti che causa un danno all’azienda, alle persone o alle cose ad esclusione degli attacchi informatici.
D25: Sicurezza informatica | E25: Attacchi informatici posti in essere da individui o organizzazioni criminali finalizzati a trafugare, disabilitare o distruggere dati o generare guasti e interruzioni ai sistemi informatici aziendali.
C26: FINANZIARI (Rischi legati agli aspetti finanziari, ad esempio mercato, credito) | D26: Contabilità e reporting finanziario | E26: Inesattezze, errori ed omissioni commessi nelle attività e nei processi di rilevazione contabile e predisposizione della reportistica direzionale (es. controllo di gestione) che compromettono l’attendibilità dei dati aziendali.
D27: Erariale patrimoniale | E27: Ogni circostanza di danneggiamento o perdita di beni o denaro generato alle finanze pubbliche da comportamenti o omissioni dolose o colpose commessi da soggetti legati all’amministrazione da un rapporto di servizio.
D28: Fiscale | E28: Inesattezze, errori ed omissioni commessi nell’esecuzione delle attività e nella gestione dei processi della fiscalità aziendale.
D29: Liquidità e credito | E29: Eccessi o carenze delle disponibilità di cassa rispetto alla pianificazione dei flussi di cassa. Riduzione del valore dei crediti iscritti in bilancio causato da inadempimenti contrattuali o abbassamento del grado di solvibilità dei debitori.
D30: Tassi d’interesse | E30: Variazioni inattese dei tassi d'interesse con ricadute sui valori iscritti tra le attività e passività di bilancio e/o sulla gestione finanziaria.
C31: STRATEGICI (Rischi derivanti da decisioni strategiche sbagliate, dalla loro attuazione inadeguata o da una governance aziendale non adeguata al raggiungimento degli obiettivi aziendali. I rischi strategici possono anche derivare dal disallineamento della strategia con la visione, la missione e i valori fondamentali dell'azienda). | D31: Comunicazione e relazioni istituzionali | E31: Ogni evento/circostanza che compromette la capacità dell’Azienda di comunicare efficacemente con stakeholder esterni e/o creare/mantenere relazioni.
D32: Governance | E32: Possibilità di incoerenza fra obiettivi strategici e mission vision aziendali. Struttura organizzativa (ruoli e responsabilità) e linee guida/principi di governo parziali o inadeguati.
D33: Immagine/Reputazione | E33: Ogni evento/circostanza che compromette l'immagine dell’Azienda davanti gli stakeholders interni o esterni rilevanti (es. dipendenti, associazioni pazienti, enti di volontariato, fornitori, autorità e istituzioni nazionali/internazionali) derivante dalla diffusione di notizie negative su media, stampa, web o altri mezzi di comunicazione.
D34: Investimenti e patrimonio | E34: Inadeguata gestione degli investimenti o del patrimonio. Inappropriate o inadeguate Iniziative di crescita organica, azioni di miglioramento o progetti di ampliamento del sistema di offerta.
D35: Pianificazione strategica | E35: Pianificazione strategica non rispondente alle priorità del sistema socio sanitario regionale o incompatibile con le risorse disponibili. Obiettivi definiti sulla base di dati/informazioni parziali, incompleti o inadeguati.
D36: Sistema di Controllo Interno | E36: Inadeguato / inefficace processo di identificazione, valutazione, gestione e monitoraggio dei rischi e/o inadeguatezza dei presidi di controllo implementati.
C37: OPERATIVI (Rischi derivanti da inadeguatezze o errori nei processi aziendali e di supporto e/o difetti nel sistema dei controlli operativi) | D37: Attività, processi e procedure | E37: Carenze nel disegno dei processi dell’Azienda, inadempienze / negligenze / errori nelle modalità di esecuzione / gestione delle attività operative e dai relativi presidi di controllo.
D38: Asset infrastrutturali e tecnologia | E38: Infrastrutture e tecnologie, diverse dalle apparecchiature sanitarie, strutturalmente inadatte (es. rete informatica che non consente di caricare i documenti sanitari, sede operativa che non garantisce la regolazione della temperatura nei locali di cura) o oggetto di malfunzionamenti (es. blocco server), danneggiamenti, errori d’uso, carente manutenzione.
D39: Business Continuity | E39: Compromissione dell'integrità e della continuità operativa di persone, asset infrastrutturali e/o tecnologici aziendali per un evento non direttamente collegato all’attività dell’Azienda.
D40: Comunicazione e relazioni | E40: Criticità o mancanza di trasparenza nelle modalità di comunicazione degli operatori con i pazienti, caregiver o familiari, prima, durante e dopo l’esecuzione dei servizi sanitari. Mancata o inadeguata comunicazione interna tra operatori e i criticità relative all'accesso alle informazioni e alle comunicazioni tra management e operatori sanitari.
D41: Continuità e coordinamento percorsi assistenziali | E41: Carenze nella definizione dei percorsi assistenziali e nelle attività di presa in carico dei bisogni assistenziali. Inefficaci o incompleti meccanismi di coordinamento tra operatori sanitari che possono pregiudicare la continuità delle cure e la qualità dell’assistenza.
D42: Edifici e spazi comuni | E42: Ogni fatto o circostanza che arreca danni a persone o cose in vari ambiti (es. ascensore, scale, corridoi, parcheggi, spazi esterni alle strutture sanitarie).
D43: Gestione apparecchiature sanitarie | E43: Malfunzionamenti dovuto a problemi tecnici di fabbricazione (non causati dall’utilizzatore), malfunzionamenti dovuto all’utilizzatore (manutenzione, impostazione, altri errori d’uso), uso in condizioni non appropriate, manutenzione inadeguata, istruzioni inadeguate, pulizia non corretta, utilizzo oltre i limiti di durata previsti delle apparecchiature sanitarie.
D44: Gestione farmaci e dispositivi medici | E44: Ogni inesattezza, incompletezza od omissione riconducibile alle fasi logistiche ed operative che assicurano l’approvvigionamento, la conservazione e la disponibilità di farmaci e dispositivi medici.
D45: Illeciti interni | E45: Qualunque azione, al di fuori dell’ambito della sicurezza dei dati e delle informazioni, nella quale un dipendente sottragga o si appropri di beni aziendali o, in alternativa, commetta atti rivolti ad arrecare un danno all’azienda.
D46: Persone e cultura | E46: Criticità derivanti dal mancato allineamento tra ruoli e personale dipendente. Scarsa diffusione e conoscenza della cultura e dei valori aziendali. Inefficacia dei programmi formativi.
D47: Informativa e reporting | E47: Carenze dei contenuti o nella gestione dei flussi informativi interni ed esterni che possono generare errori di programmazione o sanzioni per tardiva comunicazione. | F47: Informativa strategica / di programmazione | G47: Carenza o inesattezza delle informazioni del contesto interno e/o esterno che possono influire negativamente sulla programmazione.
F48: Misurazione delle performance | G48: Ogni inesattezza, incompletezza od omissione riconducibile alle attività e ai processi di misurazione delle performance.
F49: Informativa interna ed esterna | G49: Flussi informativi non correttamente gestiti in termini di modalità e contenuti.
D50: Salute, sicurezza e ambientale | E50: Infortuni, lesioni o malattie professionali ai danni del personale dipendente, inclusi l’esposizione a fattori di rischio (es. radiazioni) e gli agiti aggressivi fisici o verbali. Eventi/circostanze di responsabilità aziendale che generano un impatto negativo sull’ambiente. | F50: Atti di violenza su operatori | G50: Aggressioni fisiche o verbali a danno degli operatori delle strutture sanitarie.
F51: Rischio biologico | G51: Ogni evento dannoso per la salute dei lavoratori derivante da microrganismi, anche geneticamente modificati. Ferite da taglio e da punta con oggetti contaminati da materiale biologico.
F52: Rischio chimico | G52: Ogni evento dannoso per la salute dei lavoratori derivante dall’utilizzo o dal contatto con sostanze pericolose e dallo sversamento/spandimento di sostanze chimiche pericolose. Comprende il contatto con sostanze cancerogene e mutagene, amianto e gas anestetici.
F53: Rischio fisico | G53: Eventi dannosi per la salute dei lavoratori derivanti da agenti fisici: rumore, ultrasuoni, infrasuoni, vibrazioni, campi elettromagnetici, radiazioni ottiche di origine artificiale, microclima e atmosfera iperbariche.
F54: Rischio da atmosfera esplosiva | G54: Esplosioni causate da materiali infiammabili o instabili (es. gas, vapori, polveri)
F55: Rischio incendio | G55: Combustione non controllata che si sviluppa senza limitazioni nello spazio e nel tempo dando luogo a calore, fumo, gas e luce.
F56: Rischio da infortuni generici | G56: Ogni evento dannoso per la salute dei lavoratori connesso all’ambiente di lavoro e all’utilizzo di attrezzature (es. urto, schiacciamento, trauma muscolo-scheletrico, ferite da taglio con oggetti sterili, cadute, rischio elettrico).
F57: Rischio da movimentazione di carichi e pazienti | G57: Ogni evento dannoso per la salute dei lavoratori derivante dalla movimentazione manuale dei carichi e dei pazienti.
F58: Rischio radiazioni | G58: Ogni evento dannoso per la salute dei lavoratori derivante dall’esposizione a radiazioni ionizzanti e non ionizzanti.
F59: Rischio sociale | G59: Frequenza e numero di persone soggette ad un certo livello di danno a seguito di uno specifico evento incidentale
F60: Rischio stress lavoro correlato | G60: Percezione di squilibrio percepita dal lavoratore tra le richieste dell’ambiente lavorativo e le capacità individuali di risposta.
F61: Rischio da videoterminale | G61: Ogni evento dannoso per la salute dei lavoratori derivante dall’esposizione prolungata ai videoterminali.
C62: COMPLIANCE (Rischi legati a modifiche della legislazione in materia e alla non conformità con le normative applicabili) | D62: Anticorruzione | E62: Violazioni della Legge 190/12.
D63: Codice etico | E63: Violazione del Codice etico in vigore presso l’Azienda.
D64: Contrattualistica e controversie legali | E64: Inesattezze, errori ed omissioni commessi nelle attività e nei processi di gestione dei contratti, degli appalti e delle controversie legali.
D65: Normativa (regionale, nazionale, comunitaria) | E65: Violazione di norme imperative di legge previste a livello regionale, nazionale e comunitario, ad eccezione della Legge 190/12 e della normativa privacy e sicurezza delle informazioni.
D66: Regolamenti interni | E66: Violazione dei regolamenti aziendali.
D67: Sicurezza delle informazioni e tutela privacy | E67: Ogni circostanza di violazione della privacy o sicurezza della documentazione e delle informazioni gestite dalla struttura non riconducibili ad attacchi informatici. Inesattezze, incompletezze od omissioni nel trattamento dei dati.

Sheet Metriche di valutazione
C2: Metriche di valutazione
C5: IMPATTO
C6: SCALA | D6: VALUTAZIONE | E6: DESCRIZIONE | F6: Immagine e reputazione | G6: Compliance normativa | H6: Ambiente | I6: Salute e sicurezza | J6: Gestionale - Operativo
C7: 10 | D7: Catastrofico | E7: L'impatto sugli obiettivi aziendali e sulla gestione comporta una significativa ed estesa revisione delle strategie con un coinvolgimento straordinario di amministratori e del top management | F7: - Reputazione danneggiata a livello nazionale e/o internazionale - Reputazione danneggiata non risolvibile temporalmente - Notizie sui media nazionali e/o internazionali con esposizione mediatica di lungo periodo | G7: - Non ottemperanza di rilevante entità ad obblighi di natura contrattuale/normativa con restrizioni rilevanti per l’azienda (es. commissariamento o sanzioni interdittive che incidono sulla continuità aziendale) - Commissione di un reato che prevede la reclusione superiore a 2 anni | H7: - Impatto con significativi danni ambientali gravi e persistenti all'esterno del sito - Superamenti ingenti e sistematici di norme o limiti prescrittivi | I7: Personale/popolazione: - Infortunio mortale multiplo - Malattia professionale di più persone - Incidente che ha causato invalidità permanente/morte di una o più persone esterne al sito Pazienti: - L'evento comporta il decesso di uno o più pazienti | J7: - Impatto sugli obiettivi aziendali - Gestione richiede coinvolgimento straordinario del top management, degli amministratori ed un utilizzo straordinario di risorse aggiuntive - Gestione comporta una significativa ed estesa revisione delle strategie - Non risolvibile entro l’anno
C8: 7 | D8: Rilevante | E8: L'impatto sugli obiettivi aziendali e sulla gestione comporta una contenuta e mirata revisione delle strategie con un coinvolgimento mirato di amministratori e del top management | F8: - Reputazione danneggiata a livello nazionale e/o internazionale - Reputazione danneggiata risolvibile in massimo 1 mese - Notizie sui media nazionali e/o internazionali con esposizione mediatica di medio periodo | G8: - Non ottemperanza di significativa entità ad obblighi di natura contrattuale / normativa con restrizioni significative dell'operatività per l’azienda - Sanzioni amministrative / penali / pecuniarie di significativa entità - Commissione di un reato che prevede la reclusione fino a 2 anni | H8: - L'impatto ambientale investe ampie aree interne al sito e aree esterne - Superamenti quantitativamente importanti e ripetuti di norme o limiti prescrittivi | I8: Personale/popolazione: - Un infortunio con invalidità permanente / un morto - Un incidente che ha causato lesioni fisiche alla popolazione esterna al sito Pazienti: - L'evento comporta l'invalidità permanente o il rischio di morte (es. shock, arresto cardiaco) | J8: - Impatto sugli obiettivi aziendali - Gestione richiede un coinvolgimento notevole del top management, degli amministratori ed un utilizzo massivo di risorse aggiuntive - Gestione comporta una revisione mirata delle strategie - Risolvibile entro l’anno
C9: 5 | D9: Significativo | E9: L'impatto sugli obiettivi aziendali e sulla gestione richiede un coinvolgimento del top management significativo per essere risolto | F9: - Reputazione danneggiata a livello nazionale - Reputazione danneggiata risolvibile in massimo 15 giorni - Notizie sui media nazionali con esposizione mediatica di breve periodo | G9: - Non ottemperanza di media entità ad obblighi di natura contrattuale/normativa - Sanzioni amministrative / penali / pecuniarie di modesta entità | H9: - L'impatto ambientale investe, oltre ad aree interne al sito, anche aree esterne circostanti - Superamenti multipli di norme o limiti prescrittivi | I9: Personale/popolazione: - 1 o più infortuni con prognosi superiore a 40 giorni Pazienti: - L'evento comporta una invalidità temporanea; prolungamento della degenza > 1 mese | J9: - Impatto sugli obiettivi aziendali - Gestione richiede un coinvolgimento del top management ed utilizzo di risorse aggiuntive - Risolvibile in un mese
C10: 3 | D10: Contenuto | E10: L'impatto sugli obiettivi aziendali e sulla gestione richiede un impegno del top management per minimizzarlo | F10: - Reputazione danneggiata a livello nazionale - Reputazione danneggiata risolvibile in massimo 7 giorni - Notizie spot su media nazionali | G10: - Non ottemperanza di modesta entità ad obblighi di natura contrattuale/normativa - Sanzioni amministrative / penali / pecuniarie di moderata entità | H10: - L'impatto ambientale investe trasversalmente il sito nel suo complesso pur rimanendo su area localizzata - Singolo superamento di norme o limiti prescrittivi | I10: Personale/popolazione: - 1 o più infortuni con prognosi inferiore a 40 giorni Pazienti: - L'evento comporta un danno temporaneo; prolungamento della degenza < 1 mese | J10: - Impatto sugli obiettivi aziendali - Gestione richiede limitato impegno del top management e limitato utilizzo di risorse - Risolvibile in una settimana
C11: 2 | D11: Trascurabile | E11: L'impatto sugli obiettivi aziendali e sulla gestione può essere assorbito attraverso la normale attività | F11: - Reputazione danneggiata a livello locale/regionale - Reputazione danneggiata risolvibile in massimo 3 giorni - Notizie spot su media locali | G11: - Non ottemperanza di lieve entità ad obblighi di natura contrattuale/normativa - Sanzioni amministrative / penali / pecuniarie di trascurabile entità | H11: - Impatto ambientale temporaneo circoscritto a spazi o aree specifiche interne al sito in area non sensibile - Nessun superamento di norme o limiti prescrittivi | I11: Personale/popolazione: - Lievi infortuni nel corso dello svolgimento delle attività quotidiane Pazienti: - L'evento non comporta danni di rilievo; rende necessario un maggior monitoraggio | J11: - Impatto sugli obiettivi aziendali - Gestione assorbita attraverso la normale attività, senza l’utilizzo di ulteriori risorse - Risolvibile in giornata
C13: IMPATTO ECONOMICO
C14: SCALA | D14: VALUTAZIONE | E14: CLUSTER A | F14: CLUSTER B | G14: CLUSTER C
B15: ASST | C15: 2 | D15: Trascurabile | E15: •< 0,02% ricavi totali | F15: •< 0,015% ricavi totali | G15: •< 0,01% ricavi totali
C16: 3 | D16: Contenuto | E16: •0,02-0,25% ricavi totali | F16: •0,015-0,18% ricavi totali | G16: •0,01-0,13% ricavi totali
C17: 5 | D17: Significativo | E17: •0,25-2,5% ricavi totali | F17: •0,18-1,8% ricavi totali | G17: •0,13-1,3% ricavi totali
C18: 7 | D18: Rilevante | E18: •2,5-5% ricavi totali | F18: •1,8-3,6% ricavi totali | G18: •1,3-2,6% ricavi totali
C19: 10 | D19: Estremo | E19: •>5% ricavi totali | F19: •>3,6% ricavi totali | G19: •>2,6% ricavi totali
B20: ATS | C20: 2 | D20: Trascurabile | E20: •< 0,02% ricavi totali | F20: •<0,01% ricavi totali | G20: •<0,01% ricavi totali
C21: 3 | D21: Contenuto | E21: •0,02-0,3% ricavi totali | F21: •0,01-0,2% ricavi totali | G21: •0,01-0,15% ricavi totali
C22: 5 | D22: Significativo | E22: •0,3-3,5% ricavi totali | F22: •0,2-2% ricavi totali | G22: •0,15-1% ricavi totali
C23: 7 | D23: Rilevante | E23: •3,5-7% ricavi totali | F23: •2-4% ricavi totali | G23: •1-2% ricavi totali
C24: 10 | D24: Estremo | E24: •>7% ricavi totali | F24: •>4% ricavi totali | G24: •>2% ricavi totali
B25: IRCCS | C25: 2 | D25: Trascurabile | E25: •< 0,03% ricavi totali | F25: •< 0,02% ricavi totali | G25: •< 0,01% ricavi totali
C26: 3 | D26: Contenuto | E26: •0,03-0,2% ricavi totali | F26: •0,02-0,18% ricavi totali | G26: •0,01-0,1% ricavi totali
C27: 5 | D27: Significativo | E27: •0,2-2% ricavi totali | F27: •0,18-1,5% ricavi totali | G27: •0,1-1,2% ricavi totali
C28: 7 | D28: Rilevante | E28: •2-4% ricavi totali | F28: •1,5-3% ricavi totali | G28: •1,2-2,4% ricavi totali
C29: 10 | D29: Estremo | E29: •>4% ricavi totali | F29: •>3% ricavi totali | G29: •>2,4% ricavi totali
C31: PROBABILITA' | G31: CONTROLLI
C32: INDICE DI PROBABILITA' | D32: VALUTAZIONE | E32: PROBABILITA' DELL'EVENTO | G32: SCALA | H32: Fattore di riduzione | I32: VALUTAZIONE
C33: 6 | D33: Molto probabile | E33: - Probabilità ≥ 50% - Evento atteso almeno una volta all'anno - Evento quasi certo - Si prevede che l’evento possa verificarsi nel breve termine - L'evento si è verificato negli ultimi mesi | G33: 4 | H33: 0.1 | I33: Controllo che opera nel suo complesso in modo efficace ed efficiente assicurando il monitoraggio e il contenimento dei rischi
C34: 5 | D34: Probabile | E34: - Probabilità compresa fra il 25% ≤ x ≤ 50% - Evento atteso una volta ogni 2/3 anni - Evento molto verosimile - Si prevede che l’evento possa verificarsi nel breve / medio termine - L'evento si è verificato negli ultimi 12 mesi | G34: 3 | H34: 0.25 | I34: Controllo che opera nel suo complesso in modo efficace ed efficiente ma che presenta circosritte carenze con lieve esposizione al rischio
C35: 4 | D35: Moderatamente probabile | E35: - Probabilità 10% ≤ x ≤ 25% - Evento atteso una volta ogni 4/10 anni - Evento verosimile - Si prevede che l’evento possa verificarsi nel medio termine - L'evento si è verificato negli ultimi 3 anni | G35: 2 | H35: 0.5 | I35: Controllo con carenze localizzate con esposizione lieve al rischio o per il quale è in essere un intervento correttivo / di mitigazione in fase di conclusione (es. procedura in corso di approvazione)
C36: 3 | D36: Poco probabile | E36: - Probabilità 5% ≤ x ≤ 10% - Evento atteso una volta ogni 10/20 anni - Evento poco verosimile - Si prevede che l’evento possa verificarsi nel medio/lungo termine - L'evento si è verificato negli ultimi 5 anni | G36: 1 | H36: 0.75 | I36: Controllo che presenta significative carenze e con esposizione elevata al rischio
C37: 2 | D37: Improbabile | E37: - Probabilità ≤ 5% - Evento atteso una volta ogni 20 anni o di più - Evento molto poco verosimile - Si prevede che l'evento possa verificarsi nel lungo termine - L'evento non si è mai verificato nel passato o si è verificato una sola volta negli ultimi 10 anni | G37: 0 | H37: 1 | I37: Assenza totale di elementi di controllo, o che presenta gravi criticità, con una esposizione alta al rischio

Sheet Appoggio
B2: Processo | C2: Ruolo | D2: Risk Owner | E2: Short | G2: Categoria Rischio | H2: Short | J2: Impatto | K2: Probabilità | M2: Valutazione Controllo | N2: Fattore di riduzione | P2: Categoria Rischio Liv. 1 | Q2: Categoria Rischio Liv. 2 | R2: Categoria Rischio Liv. 3 | S2: Short
B3: Ufficio Relazioni con il Pubblico | E3: URP | G3: Rischio Clinico-Sanitario | H3: SANIT | J3: N.A. | K3: N.A. | M3: 4 | N3: 0.1 | P3: Rischio Clinico_Sanitario | Q3: Anestesiologico | R3: N.A. | S3: SANIT
B4: Bilancio e Rendicontazione | E4: BIL | G4: Rischio Esterno | H4: EST | J4: 2 | K4: 2 | M4: 3 | N4: 0.25 | P4: Rischio Clinico_Sanitario | Q4: Assistenziale | R4: N.A. | S4: SANIT
B5: Gestione Acquisti (provveditorato-economato) | E5: ACQ | G5: Rischio Finanziario | H5: FIN | J5: 3 | K5: 3 | M5: 2 | N5: 0.5 | P5: Rischio Clinico_Sanitario | Q5: Atti di autolesione e tentativi di suicidio | R5: N.A. | S5: SANIT
B6: Sistemi Informativi Aziendali | E6: SIA | G6: Rischio Strategico | H6: STR | J6: 5 | K6: 4 | M6: 1 | N6: 0.75 | P6: Rischio Clinico_Sanitario | Q6: Caduta | R6: N.A. | S6: SANIT
B7: Ingegneria Clinica | E7: ING | G7: Rischio Operativo | H7: OPE | J7: 7 | K7: 5 | M7: 0 | N7: 1 | P7: Rischio Clinico_Sanitario | Q7: Chirurgico | R7: N.A. | S7: SANIT
B8: Farmacia | E8: FAR | G8: Rischio di Compliance | H8: COMP | J8: 10 | K8: 6 | P8: Rischio Clinico_Sanitario | Q8: Diagnostico | R8: N.A. | S8: SANIT
B9: Ricerca scientifica e sperimentazioni cliniche | E9: RIC | P9: Rischio Clinico_Sanitario | Q9: Gestione / redazione documenti | R9: N.A. | S9: SANIT
B10: Affari Generali e Legali | E10: AFF.GEN | P10: Rischio Clinico_Sanitario | Q10: Identificazione del paziente | R10: N.A. | S10: SANIT
B11: Gestione delle Risorse Umane | E11: HR | P11: Rischio Clinico_Sanitario | Q11: Infezione correlata all'assistenza | R11: N.A. | S11: SANIT
B12: Ufficio Tecnico Patrimoniale | E12: UFF.TEC | P12: Rischio Clinico_Sanitario | Q12: Ostetrico e neonatale, inclusi i trigger | R12: N.A. | S12: SANIT
B13: Qualità, Risk Management e Internal Auditing | E13: QRM | P13: Rischio Clinico_Sanitario | Q13: Prevenzione | R13: N.A. | S13: SANIT
B14: Sanità pubblica veterinaria | E14: VET | P14: Rischio Clinico_Sanitario | Q14: Sperimentazioni cliniche | R14: N.A. | S14: SANIT
B15: SC Unità di Epidemiologia | E15: EPIDEM | P15: Rischio Clinico_Sanitario | Q15: Terapeutico | R15: N.A. | S15: SANIT
B16: Medicina preventiva di comunità - screening | E16: SCREENING | P16: Rischio Clinico_Sanitario | Q16: Trasfusionale | R16: N.A. | S16: SANIT
B17: Gestione Operativa | E17: GEST.OP | P17: Rischio Esterno | Q17: Contesto socio-economico nazionale e regionale | R17: N.A. | S17: EST
B18: Dipartimento Igiene e Prevenzione Sanitaria | E18: IGIENE | P18: Rischio Esterno | Q18: Eventi naturali o accidentali | R18: N.A. | S18: EST
B19: Controllo di gestione | E19: C.GEST | P19: Rischio Esterno | Q19: Evoluzione del contesto normativo | R19: N.A. | S19: EST
B20: Trasporto STAM/STEN | E20: STAM/STEN | P20: Rischio Esterno | Q20: Gestione Terze Parti | R20: N.A. | S20: EST
... B26: Percorso Attuativo della Certificabilità | E26: PAC | P26: Rischio Finanziario | Q26: Liquidità e credito | R26: N.A. | S26: FIN
P27: Rischio Finanziario | Q27: Tassi d’interesse | R27: N.A. | S27: FIN
P28: Rischio Strategico | Q28: Comunicazione e relazioni istituzionali | R28: N.A. | S28: STR
P29: Rischio Strategico | Q29: Governance | R29: N.A. | S29: STR
P30: Rischio Strategico | Q30: Immagine/Reputazione | R30: N.A. | S30: STR
P31: Rischio Strategico | Q31: Investimenti e patrimonio | R31: N.A. | S31: STR
P32: Rischio Strategico | Q32: Pianificazione strategica | R32: N.A. | S32: STR
P33: Rischio Strategico | Q33: Sistema di Controllo Interno | R33: N.A. | S33: STR
P34: Rischio Operativo | Q34: Attività, processi e procedure | R34: N.A. | S34: OPE
P35: Rischio Operativo | Q35: Asset infrastrutturali e tecnologia | R35: N.A. | S35: OPE
P36: Rischio Operativo | Q36: Business Continuity | R36: N.A. | S36: OPE
P37: Rischio Operativo | Q37: Comunicazione e relazioni | R37: N.A. | S37: OPE
P38: Rischio Operativo | Q38: Continuità e coordinamento percorsi assistenziali | R38: N.A. | S38: OPE
... P68: Rischio Operativo | Q68: Salute sicurezza e ambiente | R68: Rischio da videoterminale | S68: OPE

Sheet Fonti e note
A1: Registro | B1: Fonte | C1: Contenuto utilizzato | D1: Note
A2: RISK REGISTER - PAC AREA D IMMOBILIZZAZIONI | B2: 1.3_Gestione_Apparecchiature_Elettromedicali_rev01 (PO 595).pdf | C2: Procedura operativa: ciclo di vita apparecchiature, collaudo, inventario, dismissioni, controlli periodici, conservazione documentale. | D2: Base per scenari, cause, presidi e responsabilità.
A3: RISK REGISTER - PAC AREA D IMMOBILIZZAZIONI | B3: Formazione HERM 2026 (1).pdf | C3: Modello HERM: tassonomia rischi, metriche impatto/probabilità/controlli, calcolo rischio inerente/residuo e trattamento. | D3: Base metodologica per valutazioni e formule.
A4: RISK REGISTER - PAC AREA D IMMOBILIZZAZIONI | B4: Riferimento anno precedente - rischi Ingegneria Clinica | C4: Rischi storici su manutenzione, collaudo, formazione, avvisi sicurezza, prove/visioni, dismissioni e terze parti. | D4: Riutilizzato e aggiornato alla PO 595.
A5: RISK REGISTER - PAC AREA D IMMOBILIZZAZIONI | B5: 2026_05_18Risk_Register_PAC_compilato.xlsx | C5: Template originale del Risk Register. | D5: Struttura, formule e fogli di supporto preservati.
A6: RISK REGISTER - PAC AREA D IMMOBILIZZAZIONI | D6: Perimetro allargato al PAC Area D - Immobilizzazioni, con focus sui punti di contatto con Ingegneria Clinica e ciclo di vita delle apparecchiature elettromedicali.
